Workbook

Sheet Dashboard
B2: Scope 3 Emissions Dashboard – FY2023
B3: GHG Protocol Corporate Value Chain (Scope 3) Standard | Cat 15 per PCAF (2022) | All figures tCO₂e unless stated | Linked live to 'Exec Summary' and category tabs
B5: Total Scope 3 | D5: Downstream share | F5: Upstream share | H5: Top-2 concentration | J5: Cat 11 direct use-phase | L5: Holdings at PCAF DQ 4–5
B6: ='Exec Summary'!D21/1000000 -> 68.088814 | D6: ='Exec Summary'!E30 -> 0.99869313 | F6: ='Exec Summary'!E31 -> 0.0013068669 | H6: ='Exec Summary'!E39 -> 0.99773982 | J6: ='Exec Summary'!E25 -> 0.87660593 | L6: ='Exec Summary'!E38 -> 0.39
B7: All 15 categories, tCO₂e ÷ 1m | D7: Cat 9–15 | F7: Cat 1–8 | H7: Cat 11 + Cat 15 | J7: Fuel combustion share of Cat 11 | L7: Cat 15 – weak data quality
B9: 1. Emissions by category (ranked) | J9: Concentration
B10: Cat # | C10: Category | F10: Stream | G10: tCO₂e | H10: % of total
B11: ='Exec Summary'!A6 -> 11 | C11: ='Exec Summary'!B6 -> Use of Sold Products | F11: ='Exec Summary'!C6 -> Downstream | G11: ='Exec Summary'!D6 -> 62357323 | H11: ='Exec Summary'!E6 -> 0.91582331
B12: ='Exec Summary'!A7 -> 15 | C12: ='Exec Summary'!B7 -> Investments | F12: ='Exec Summary'!C7 -> Downstream | G12: ='Exec Summary'!D7 -> 5577598 | H12: ='Exec Summary'!E7 -> 0.081916509
B13: ='Exec Summary'!A8 -> 4 | C13: ='Exec Summary'!B8 -> Upstream Transportation & Distribution | F13: ='Exec Summary'!C8 -> Upstream | G13: ='Exec Summary'!D8 -> 35714.794 | H13: ='Exec Summary'!E8 -> 0.00052453247
B14: ='Exec Summary'!A9 -> 2 | C14: ='Exec Summary'!B9 -> Capital Goods | F14: ='Exec Summary'!C9 -> Upstream | G14: ='Exec Summary'!D9 -> 33680.859 | H14: ='Exec Summary'!E9 -> 0.00049466067
B15: ='Exec Summary'!A10 -> 13 | C15: ='Exec Summary'!B10 -> Downstream Leased Assets | F15: ='Exec Summary'!C10 -> Downstream | G15: ='Exec Summary'!D10 -> 31572.195 | H15: ='Exec Summary'!E10 -> 0.00046369137
B16: ='Exec Summary'!A11 -> 8 | C16: ='Exec Summary'!B11 -> Upstream Leased Assets | F16: ='Exec Summary'!C11 -> Upstream | G16: ='Exec Summary'!D11 -> 15628.31 | H16: ='Exec Summary'!E11 -> 0.0002295283
B17: ='Exec Summary'!A12 -> 12 | C17: ='Exec Summary'!B12 -> End-of-Life Treatment of Sold Products | F17: ='Exec Summary'!C12 -> Downstream | G17: ='Exec Summary'!D12 -> 15163.005 | H17: ='Exec Summary'!E12 -> 0.00022269451
B18: ='Exec Summary'!A13 -> 9 | C18: ='Exec Summary'!B13 -> Downstream Transportation & Distribution | F18: ='Exec Summary'!C13 -> Downstream | G18: ='Exec Summary'!D13 -> 12124.43 | H18: ='Exec Summary'!E13 -> 0.00017806786
B19: ='Exec Summary'!A14 -> 14 | C19: ='Exec Summary'!B14 -> Franchises | F19: ='Exec Summary'!C14 -> Downstream | G19: ='Exec Summary'!D14 -> 5984.2672 | H19: ='Exec Summary'!E14 -> 8.7889138e-05
B20: ='Exec Summary'!A15 -> 3 | C20: ='Exec Summary'!B15 -> Fuel- & Energy-Related Activities | F20: ='Exec Summary'!C15 -> Upstream | G20: ='Exec Summary'!D15 -> 1865.6269 | H20: ='Exec Summary'!E15 -> 2.7399903e-05
B21: ='Exec Summary'!A16 -> 1 | C21: ='Exec Summary'!B16 -> Purchased Goods & Services | F21: ='Exec Summary'!C16 -> Upstream | G21: ='Exec Summary'!D16 -> 1819.599 | H21: ='Exec Summary'!E16 -> 2.6723905e-05
B22: ='Exec Summary'!A17 -> 6 | C22: ='Exec Summary'!B17 -> Business Travel | F22: ='Exec Summary'!C17 -> Upstream | G22: ='Exec Summary'!D17 -> 144.65021 | H22: ='Exec Summary'!E17 -> 2.1244343e-06
... B25: ='Exec Summary'!A20 -> 5 | C25: ='Exec Summary'!B20 -> Waste Generated in Operations | F25: ='Exec Summary'!C20 -> Upstream | G25: ='Exec Summary'!D20 -> 0.98433 | H25: ='Exec Summary'!E20 -> 1.445656e-08
B26: Total | C26: Scope 3 – all 15 categories | G26: =SUM(G11:G25) -> 68088814 | H26: =SUM(H11:H25) -> 1
B28: 2. What drives the footprint
B47: 3. Rest of the inventory & financed-emissions data quality
B80: Chart data (linked – do not overwrite)
B82: Concentration | C82: tCO₂e | E82: Product key | F82: Product type | G82: tCO₂e | I82: Sector | J82: tCO₂e | L82: PCAF DQ score | M82: # holdings | N82: tCO₂e
B83: Cat 11 Use of sold products | C83: =G11 -> 62357323 | E83: Industrial | F83: Industrial equipment (fuel) | G83: =SUMIF('Cat 11 – Use of Sold Products'!$C$4:$C$103,E83,'Cat 11 – Use of Sold Products'!$Q$4:$Q$103) -> 41921162 | I83: Utilities | J83: =SUMIF('Cat 15 – Investments'!$F$4:$F$103,I83,'Cat 15 – Investments'!$N$4:$N$103) -> 1029381.4 | L83: 1 | M83: =COUNTIF('Cat 15 – Investments'!$Q$4:$Q$103,L83) -> 23 | N83: =SUMIF('Cat 15 – Investments'!$Q$4:$Q$103,L83,'Cat 15 – Investments'!$N$4:$N$103) -> 1675341.9
B84: Cat 15 Investments | C84: =G12 -> 5577598 | E84: Petrol | F84: Petrol engines / vehicles | G84: =SUMIF('Cat 11 – Use of Sold Products'!$C$4:$C$103,E84,'Cat 11 – Use of Sold Products'!$Q$4:$Q$103) -> 6714916.3 | I84: Oil & Gas | J84: =SUMIF('Cat 15 – Investments'!$F$4:$F$103,I84,'Cat 15 – Investments'!$N$4:$N$103) -> 725034.7 | L84: 2 | M84: =COUNTIF('Cat 15 – Investments'!$Q$4:$Q$103,L84) -> 20 | N84: =SUMIF('Cat 15 – Investments'!$Q$4:$Q$103,L84,'Cat 15 – Investments'!$N$4:$N$103) -> 1355682
B85: Other 13 categories | C85: =G26-G11-G12 -> 153893.18 | E85: Diesel | F85: Diesel engines / vehicles | G85: =SUMIF('Cat 11 – Use of Sold Products'!$C$4:$C$103,E85,'Cat 11 – Use of Sold Products'!$Q$4:$Q$103) -> 6026720.3 | I85: Agriculture | J85: =SUMIF('Cat 15 – Investments'!$F$4:$F$103,I85,'Cat 15 – Investments'!$N$4:$N$103) -> 480242.69 | L85: 3 | M85: =COUNTIF('Cat 15 – Investments'!$Q$4:$Q$103,L85) -> 18 | N85: =SUMIF('Cat 15 – Investments'!$Q$4:$Q$103,L85,'Cat 15 – Investments'!$N$4:$N$103) -> 587766.23
E86: Heat | F86: Heat pumps | G86: =SUMIF('Cat 11 – Use of Sold Products'!$C$4:$C$103,E86,'Cat 11 – Use of Sold Products'!$Q$4:$Q$103) -> 3072232 | I86: Cement | J86: =SUMIF('Cat 15 – Investments'!$F$4:$F$103,I86,'Cat 15 – Investments'!$N$4:$N$103) -> 474374.47 | L86: 4 | M86: =COUNTIF('Cat 15 – Investments'!$Q$4:$Q$103,L86) -> 22 | N86: =SUMIF('Cat 15 – Investments'!$Q$4:$Q$103,L86,'Cat 15 – Investments'!$N$4:$N$103) -> 840008.39
B87: Other 13 categories | E87: Air | F87: Air conditioners | G87: =SUMIF('Cat 11 – Use of Sold Products'!$C$4:$C$103,E87,'Cat 11 – Use of Sold Products'!$Q$4:$Q$103) -> 1800636.5 | I87: Transport | J87: =SUMIF('Cat 15 – Investments'!$F$4:$F$103,I87,'Cat 15 – Investments'!$N$4:$N$103) -> 462477.72 | L87: 5 | M87: =COUNTIF('Cat 15 – Investments'!$Q$4:$Q$103,L87) -> 17 | N87: =SUMIF('Cat 15 – Investments'!$Q$4:$Q$103,L87,'Cat 15 – Investments'!$N$4:$N$103) -> 1118799.3
B88: Category | C88: tCO₂e | E88: Electric | F88: Electric vehicles / equipment | G88: =SUMIF('Cat 11 – Use of Sold Products'!$C$4:$C$103,E88,'Cat 11 – Use of Sold Products'!$Q$4:$Q$103) -> 1789617.7 | I88: Mining | J88: =SUMIF('Cat 15 – Investments'!$F$4:$F$103,I88,'Cat 15 – Investments'!$N$4:$N$103) -> 382526.75
B89: ="Cat "&B13&" "&C13 -> Cat 4 Upstream Transportation & Distribution | C89: =G13 -> 35714.794 | E89: Refrigerator | F89: Refrigerators | G89: =SUMIF('Cat 11 – Use of Sold Products'!$C$4:$C$103,E89,'Cat 11 – Use of Sold Products'!$Q$4:$Q$103) -> 650025.02 | I89: Automotive | J89: =SUMIF('Cat 15 – Investments'!$F$4:$F$103,I89,'Cat 15 – Investments'!$N$4:$N$103) -> 374186.7
B90: ="Cat "&B14&" "&C14 -> Cat 2 Capital Goods | C90: =G14 -> 33680.859 | E90: Washing | F90: Washing machines | G90: =SUMIF('Cat 11 – Use of Sold Products'!$C$4:$C$103,E90,'Cat 11 – Use of Sold Products'!$Q$4:$Q$103) -> 320117.46 | I90: Retail | J90: =SUMIF('Cat 15 – Investments'!$F$4:$F$103,I90,'Cat 15 – Investments'!$N$4:$N$103) -> 332203.02
B91: ="Cat "&B15&" "&C15 -> Cat 13 Downstream Leased Assets | C91: =G15 -> 31572.195 | E91: LED | F91: LED lighting | G91: =SUMIF('Cat 11 – Use of Sold Products'!$C$4:$C$103,E91,'Cat 11 – Use of Sold Products'!$Q$4:$Q$103) -> 48014.65 | I91: Aviation | J91: =SUMIF('Cat 15 – Investments'!$F$4:$F$103,I91,'Cat 15 – Investments'!$N$4:$N$103) -> 309671.04
B92: ="Cat "&B16&" "&C16 -> Cat 8 Upstream Leased Assets | C92: =G16 -> 15628.31 | E92: Laptop | F92: Laptops | G92: =SUMIF('Cat 11 – Use of Sold Products'!$C$4:$C$103,E92,'Cat 11 – Use of Sold Products'!$Q$4:$Q$103) -> 13880.82 | I92: Pharmaceuticals | J92: =SUMIF('Cat 15 – Investments'!$F$4:$F$103,I92,'Cat 15 – Investments'!$N$4:$N$103) -> 276842.95
B93: ="Cat "&B17&" "&C17 -> Cat 12 End-of-Life Treatment of Sold Products | C93: =G17 -> 15163.005 | I93: Real Estate | J93: =SUMIF('Cat 15 – Investments'!$F$4:$F$103,I93,'Cat 15 – Investments'!$N$4:$N$103) -> 237144.72
B94: ="Cat "&B18&" "&C18 -> Cat 9 Downstream Transportation & Distribution | C94: =G18 -> 12124.43 | I94: Technology | J94: =SUMIF('Cat 15 – Investments'!$F$4:$F$103,I94,'Cat 15 – Investments'!$N$4:$N$103) -> 231883.04
B95: ="Cat "&B19&" "&C19 -> Cat 14 Franchises | C95: =G19 -> 5984.2672 | I95: Steel | J95: =SUMIF('Cat 15 – Investments'!$F$4:$F$103,I95,'Cat 15 – Investments'!$N$4:$N$103) -> 161225.2
B96: ="Cat "&B20&" "&C20 -> Cat 3 Fuel- & Energy-Related Activities | C96: =G20 -> 1865.6269 | I96: Financial Services | J96: =SUMIF('Cat 15 – Investments'!$F$4:$F$103,I96,'Cat 15 – Investments'!$N$4:$N$103) -> 87210.57
B97: ="Cat "&B21&" "&C21 -> Cat 1 Purchased Goods & Services | C97: =G21 -> 1819.599 | I97: Chemicals | J97: =SUMIF('Cat 15 – Investments'!$F$4:$F$103,I97,'Cat 15 – Investments'!$N$4:$N$103) -> 13192.98
B98: ="Cat "&B22&" "&C22 -> Cat 6 Business Travel | C98: =G22 -> 144.65021
B99: ="Cat "&B23&" "&C23 -> Cat 7 Employee Commuting | C99: =G23 -> 128.19465
B100: ="Cat "&B24&" "&C24 -> Cat 10 Processing of Sold Products | C100: =G24 -> 66.2666
B101: ="Cat "&B25&" "&C25 -> Cat 5 Waste Generated in Operations | C101: =G25 -> 0.98433

Sheet Exec Summary
A1: Scope 3 Inventory – Executive Summary (FY2023)
A2: Basis: GHG Protocol Corporate Value Chain (Scope 3) Standard; Cat 15 per PCAF (2022). All figures tCO₂e unless stated. Practice dataset: 100 rows per category.
A4: 1. Scope 3 footprint by category
A5: Cat # | B5: Category | C5: Up / Down | D5: Emissions (tCO₂e) | E5: % of total | F5: Method applied
A6: 11 | B6: Use of Sold Products | C6: Downstream | D6: =SUM('Cat 11 – Use of Sold Products'!Q4:Q103) -> 62357323 | E6: =D6/$D$21 -> 0.91582331 | F6: Direct + indirect use-phase
A7: 15 | B7: Investments | C7: Downstream | D7: =SUM('Cat 15 – Investments'!N4:N103) -> 5577598 | E7: =D7/$D$21 -> 0.081916509 | F7: PCAF attribution factor
A8: 4 | B8: Upstream Transportation & Distribution | C8: Upstream | D8: =SUM('Cat 4 – Upstream Transportat'!O4:O103) -> 35714.794 | E8: =D8/$D$21 -> 0.00052453247 | F8: Distance-based (tonne-km)
A9: 2 | B9: Capital Goods | C9: Upstream | D9: =SUM('Cat 2 – Capital Goods'!N4:N103) -> 33680.859 | E9: =D9/$D$21 -> 0.00049466067 | F9: Mass-based
A10: 13 | B10: Downstream Leased Assets | C10: Downstream | D10: =SUM('Cat 13 – Downstream Leased As'!R4:R103) -> 31572.195 | E10: =D10/$D$21 -> 0.00046369137 | F10: Asset-specific energy
A11: 8 | B11: Upstream Leased Assets | C11: Upstream | D11: =SUM('Cat 8 – Upstream Leased Asse'!R4:R103) -> 15628.31 | E11: =D11/$D$21 -> 0.0002295283 | F11: Asset-specific energy
A12: 12 | B12: End-of-Life Treatment of Sold Products | C12: Downstream | D12: =SUM('Cat 12 – End-of-Life Treatmen'!T4:T103) -> 15163.005 | E12: =D12/$D$21 -> 0.00022269451 | F12: Waste-type-specific
A13: 9 | B13: Downstream Transportation & Distribution | C13: Downstream | D13: =SUM('Cat 9 – Downstream Transport'!T4:T103) -> 12124.43 | E13: =D13/$D$21 -> 0.00017806786 | F13: Distance-based + warehousing
A14: 14 | B14: Franchises | C14: Downstream | D14: =SUM('Cat 14 – Franchises'!S4:S103) -> 5984.2672 | E14: =D14/$D$21 -> 8.7889138e-05 | F14: Franchisee Scope 1+2
A15: 3 | B15: Fuel- & Energy-Related Activities | C15: Upstream | D15: =SUM('Cat 3 – Fuel- and Energy-Rel'!O4:O103) -> 1865.6269 | E15: =D15/$D$21 -> 2.7399903e-05 | F15: Upstream fuel + T&D losses
A16: 1 | B16: Purchased Goods & Services | C16: Upstream | D16: =SUM('Cat 1 – Purchased Goods & Se'!R4:R103) -> 1819.599 | E16: =D16/$D$21 -> 2.6723905e-05 | F16: Average-data (mass)
A17: 6 | B17: Business Travel | C17: Upstream | D17: =SUM('Cat 6 – Business Travel'!R4:R103) -> 144.65021 | E17: =D17/$D$21 -> 2.1244343e-06 | F17: Distance-based + hotel nights
A18: 7 | B18: Employee Commuting | C18: Upstream | D18: =SUM('Cat 7 – Employee Commuting'!S4:S103) -> 128.19465 | E18: =D18/$D$21 -> 1.8827564e-06 | F18: Distance-based + WFH
A19: 10 | B19: Processing of Sold Products | C19: Downstream | D19: =SUM('Cat 10 – Processing of Sold P'!M4:M103) -> 66.2666 | E19: =D19/$D$21 -> 9.7323769e-07 | F19: Average-data (process EF)
A20: 5 | B20: Waste Generated in Operations | C20: Upstream | D20: =SUM('Cat 5 – Waste Generated in O'!L4:L103) -> 0.98433 | E20: =D20/$D$21 -> 1.445656e-08 | F20: Waste-type-specific – see flag F2
A21: Total | B21: Scope 3 – all 15 categories | D21: =SUM(D6:D20) -> 68088814 | E21: =SUM(E6:E20) -> 1
A23: 2. Where the footprint actually sits – drivers
A24: Metric | D24: tCO₂e | E24: % of parent
A25: Cat 11 – Fuel combustion in sold products (direct use-phase) | D25: =SUM('Cat 11 – Use of Sold Products'!P4:P103) -> 54662799 | E25: =D25/$D$6 -> 0.87660593
A26: Cat 11 – Electricity consumed by sold products (indirect use-phase) | D26: =SUM('Cat 11 – Use of Sold Products'!O4:O103) -> 7694524.1 | E26: =D26/$D$6 -> 0.12339407
A27: Cat 4 – Air freight share of upstream logistics | D27: =SUMIF('Cat 4 – Upstream Transportat'!I4:I103,"Air",'Cat 4 – Upstream Transportat'!O4:O103) -> 25868.142 | E27: =D27/$D$8 -> 0.72429767
A28: Cat 15 – Utilities + Oil & Gas financed emissions | D28: =SUMIF('Cat 15 – Investments'!F4:F103,"Utilities",'Cat 15 – Investments'!N4:N103)+SUMIF('Cat 15 – Investments'!F4:F103,"Oil & Gas",'Cat 15 – Investments'!N4:N103) -> 1754416.1 | E28: =D28/$D$7 -> 0.31454689
A29: Cat 12 – Landfill share of end-of-life emissions | D29: =SUM('Cat 12 – End-of-Life Treatmen'!Q4:Q103) -> 7828.7828 | E29: =D29/$D$12 -> 0.51630814
A30: Total downstream (Cat 9–15) | D30: =SUMIF($C$6:$C$20,"Downstream",$D$6:$D$20) -> 67999831 | E30: =D30/$D$21 -> 0.99869313
A31: Total upstream (Cat 1–8) | D31: =SUMIF($C$6:$C$20,"Upstream",$D$6:$D$20) -> 88983.017 | E31: =D31/$D$21 -> 0.0013068669
A33: 3. Data quality & assurance flags
A34: Flag | B34: Issue | D34: Measure | E34: Value | F34: Implication
A35: F1 | B35: Spend-based EFs are ~2 orders of magnitude below EEIO norms (e.g. Cat 4 freight EF ≈0.0014 vs GLEC/EEIO ≈0.2–1.0 kg CO₂e/USD). Spend method is unusable as reported. | D35: Cat 4: distance-based ÷ spend-based | E35: =D8/SUM('Cat 4 – Upstream Transportat'!R4:R103) -> 24350.94 | F35: Rebuild spend EF library before any spend-based reporting
A36: F2 | B36: Cat 5 waste EFs are labelled kg CO₂e/tonne but carry per-kg magnitudes (0.07–0.77 vs GHG Protocol landfill 0.45–1.30 kg CO₂e/kg). Category understated ~1,000×. | D36: Cat 5 as reported vs unit-corrected | E36: =TEXT(D20,"0.0")&" vs "&TEXT(D20*1000,"#,##0") -> 1.0 vs 984 | F36: Correct unit basis; immaterial to total but a visible audit finding
A37: F3 | B37: Cat 1 method divergence: average-data result is multiples of the spend-based result, and only a minority of lines have supplier primary data. | D37: Cat 1 lines with primary data | E37: =COUNTIF('Cat 1 – Purchased Goods & Se'!S4:S103,"Y")/COUNTA('Cat 1 – Purchased Goods & Se'!S4:S103) -> 0.22 | F37: Supplier engagement needed to move to hybrid method
A38: F4 | B38: PCAF data quality on financed emissions is weak – a large share of the portfolio sits at score 4–5 (modelled / estimated). | D38: Cat 15 holdings at PCAF DQ 4–5 | E38: =COUNTIFS('Cat 15 – Investments'!Q4:Q103,">=4")/COUNTA('Cat 15 – Investments'!Q4:Q103) -> 0.39 | F38: Target DQ 1–2 for top exposures ahead of assurance
A39: F5 | B39: Concentration risk: two categories drive the inventory, so total footprint is only as reliable as their inputs (product lifetime, usage, grid EF, EVIC). | D39: Cat 11 + Cat 15 share of total | E39: =(D6+D7)/D21 -> 0.99773982 | F39: Focus assurance and decarbonisation effort here

Sheet Cat 1 – Purchased Goods & Se
A1: Scope 3 – Category 1: Purchased Goods & Services
A2: GHG Protocol Corporate Value Chain (Scope 3) Accounting and Reporting Standard | Practice Dataset – 100 Rows
A3: Row # | B3: Reporting Year | C3: Quarter | D3: Supplier Name | E3: Country of Origin | F3: Category of Good/Service | G3: Product / Service Description | H3: Purchase Order # | I3: Invoice Date | J3: Quantity Purchased | K3: Unit | L3: Unit Price (USD) | M3: Total Spend (USD) | N3: Spend-Based EF (kg CO₂e/USD) | O3: Avg-Data EF (kg CO₂e/kg) | P3: Mass Purchased (kg) | Q3: Emissions – Spend Method (tCO₂e) | R3: Emissions – Avg-Data Method (tCO₂e) | S3: Primary Data Available (Y/N) | T3: Data Quality Notes
A4: 1 | B4: 2023 | C4: Q1 | D4: Supplier R | E4: USA | F4: Office Supplies | G4: Ceramic Tiles | H4: PO-10000 | I4: 17-Jan-2023 | J4: 6430.3 | K4: kg | L4: 12.99 | M4: 83529.6 | N4: 0.00242 | O4: 8.969 | P4: 1154.9 | Q4: 0.2021 | R4: 10.3583 | S4: Y | T4: Supplier invoice
A5: 2 | B5: 2023 | C5: Q2 | D5: Supplier R | E5: Singapore | F5: Consulting | G5: Carbon Fibre | H5: PO-10001 | I5: 29-Oct-2023 | J5: 2264.5 | K5: kg | L5: 252.92 | M5: 572737.34 | N5: 0.0005 | O5: 7.974 | P5: 1034.2 | Q5: 0.2864 | R5: 8.2467 | S5: N | T5: Supplier invoice
A6: 3 | B6: 2023 | C6: Q3 | D6: Supplier K | E6: USA | F6: Packaging | G6: Lubricant Oil | H6: PO-10002 | I6: 19-Feb-2023 | J6: 7612.2 | K6: kg | L6: 80.25 | M6: 610879.05 | N6: 0.00355 | O6: 2.976 | P6: 1425.5 | Q6: 2.1686 | R6: 4.2423 | S6: N | T6: GHG Protocol EEIO
A7: 4 | B7: 2023 | C7: Q4 | D7: Supplier M | E7: USA | F7: Food & Beverage | G7: Electronic Components | H7: PO-10003 | I7: 18-Nov-2023 | J7: 6076.9 | K7: kg | L7: 403.66 | M7: 2453001.5 | N7: 0.00592 | O7: 11.691 | P7: 2704.3 | Q7: 14.5218 | R7: 31.616 | S7: N | T7: Industry average
A8: 5 | B8: 2023 | C8: Q1 | D8: Supplier H | E8: Netherlands | F8: Packaging | G8: Lubricant Oil | H8: PO-10004 | I8: 23-May-2023 | J8: 7075.3 | K8: kg | L8: 23.39 | M8: 165491.27 | N8: 0.00205 | O8: 1.418 | P8: 1482.5 | Q8: 0.3393 | R8: 2.1022 | S8: N | T8: GHG Protocol EEIO
A9: 6 | B9: 2023 | C9: Q2 | D9: Supplier C | E9: UAE | F9: IT Services | G9: Audit Services | H9: PO-10005 | I9: 06-May-2023 | J9: 1710.3 | K9: kg | L9: 177.96 | M9: 304364.99 | N9: 0.00546 | O9: 8.361 | P9: 3524 | Q9: 1.6618 | R9: 29.4642 | S9: N | T9: Ecoinvent 3.9
A10: 7 | B10: 2023 | C10: Q3 | D10: Supplier B | E10: UK | F10: Raw Material | G10: Packaging Material | H10: PO-10006 | I10: 25-Jul-2023 | J10: 3856.6 | K10: kg | L10: 494.77 | M10: 1908130 | N10: 0.00523 | O10: 8.373 | P10: 2806.9 | Q10: 9.9795 | R10: 23.5022 | S10: N | T10: Supplier invoice
A11: 8 | B11: 2023 | C11: Q4 | D11: Supplier M | E11: Mexico | F11: Utilities | G11: Glass Panels | H11: PO-10007 | I11: 16-May-2023 | J11: 2188.7 | K11: kg | L11: 471.48 | M11: 1031928.3 | N11: 0.00705 | O11: 8.038 | P11: 1607.7 | Q11: 7.2751 | R11: 12.9227 | S11: N | T11: Industry average
A12: 9 | B12: 2023 | C12: Q1 | D12: Supplier L | E12: UK | F12: IT Services | G12: Legal Services | H12: PO-10008 | I12: 10-Sep-2023 | J12: 7475.4 | K12: kg | L12: 269.72 | M12: 2016264.9 | N12: 0.00605 | O12: 7.211 | P12: 2170.7 | Q12: 12.1984 | R12: 15.6529 | S12: Y | T12: Supplier invoice
A13: 10 | B13: 2023 | C13: Q2 | D13: Supplier M | E13: Singapore | F13: Office Supplies | G13: Carbon Fibre | H13: PO-10009 | I13: 28-Sep-2023 | J13: 8624.9 | K13: kg | L13: 76.84 | M13: 662737.32 | N13: 0.00153 | O13: 7.359 | P13: 3418.4 | Q13: 1.014 | R13: 25.156 | S13: N | T13: Supplier invoice
A14: 11 | B14: 2023 | C14: Q3 | D14: Supplier K | E14: USA | F14: Chemicals | G14: Ceramic Tiles | H14: PO-10010 | I14: 22-Mar-2023 | J14: 6834.8 | K14: kg | L14: 57.72 | M14: 394504.66 | N14: 0.00711 | O14: 9.339 | P14: 3766.8 | Q14: 2.8049 | R14: 35.1781 | S14: N | T14: Supplier invoice
A15: 12 | B15: 2023 | C15: Q4 | D15: Supplier D | E15: Netherlands | F15: Chemicals | G15: Legal Services | H15: PO-10011 | I15: 08-Nov-2023 | J15: 9542.8 | K15: kg | L15: 437.99 | M15: 4179651 | N15: 0.00233 | O15: 2.554 | P15: 2527.9 | Q15: 9.7386 | R15: 6.4563 | S15: N | T15: Industry average
... A103: 100 | B103: 2023 | C103: Q4 | D103: Supplier K | E103: UAE | F103: IT Services | G103: Copper Wire | H103: PO-10099 | I103: 06-Mar-2023 | J103: 4320.1 | K103: kg | L103: 54.43 | M103: 235143.04 | N103: 0.00579 | O103: 10.842 | P103: 2245.6 | Q103: 1.3615 | R103: 24.3468 | S103: N | T103: GHG Protocol EEIO

Sheet Cat 2 – Capital Goods
A1: Scope 3 – Category 2: Capital Goods
A2: GHG Protocol Corporate Value Chain (Scope 3) Accounting and Reporting Standard | Practice Dataset – 100 Rows
A3: Row # | B3: Reporting Year | C3: Asset Name | D3: Asset Category | E3: Supplier / Manufacturer | F3: Country of Manufacture | G3: Purchase Date | H3: Asset Life (Years) | I3: Capex (USD) | J3: Mass of Asset (tonne) | K3: Spend-Based EF (kg CO₂e/USD) | L3: Mass-Based EF (kg CO₂e/tonne) | M3: Emissions – Spend Method (tCO₂e) | N3: Emissions – Mass Method (tCO₂e) | O3: Supplier EPD Available (Y/N) | P3: Asset Serial / PO # | Q3: Notes
A4: 1 | B4: 2023 | C4: Assembly Robot | D4: IT Hardware | E4: Supplier D | F4: Netherlands | G4: 02-Dec-2023 | H4: 25 | I4: 764904 | J4: 30.07 | K4: 0.00153 | L4: 13.232 | M4: 1.1703 | N4: 397.8862 | O4: N | P4: SN-50000 | Q4: Expansion
A5: 2 | B5: 2023 | C5: Air Compressor | D5: Solar PV Installation | E5: Supplier N | F5: Canada | G5: 18-Feb-2023 | H5: 15 | I5: 1731657 | J5: 21.79 | K5: 0.00361 | L5: 11.049 | M5: 6.2513 | N5: 240.7577 | O5: N | P5: SN-50001 | Q5: Replacement
A6: 3 | B6: 2023 | C6: Injection Moulding Press | D6: IT Hardware | E6: Supplier C | F6: USA | G6: 10-Aug-2023 | H6: 8 | I6: 1331890 | J6: 19.03 | K6: 0.00103 | L6: 23.167 | M6: 1.3718 | N6: 440.868 | O6: N | P6: SN-50002 | Q6: Expansion
A7: 4 | B7: 2023 | C7: Laptop Fleet | D7: HVAC System | E7: Supplier D | F7: Singapore | G7: 01-Jul-2023 | H7: 26 | I7: 748430 | J7: 6.94 | K7: 0.00071 | L7: 23.968 | M7: 0.5314 | N7: 166.3379 | O7: N | P7: SN-50003 | Q7: Expansion
A8: 5 | B8: 2023 | C8: Laptop Fleet | D8: Building/Construction | E8: Supplier E | F8: France | G8: 04-Sep-2023 | H8: 12 | I8: 107635 | J8: 14.74 | K8: 0.00159 | L8: 3.666 | M8: 0.1711 | N8: 54.0368 | O8: Y | P8: SN-50004 | Q8: Replacement
A9: 6 | B9: 2023 | C9: Assembly Robot | D9: Forklift | E9: Supplier T | F9: UAE | G9: 12-Dec-2023 | H9: 25 | I9: 1691520 | J9: 18.69 | K9: 0.00317 | L9: 14.864 | M9: 5.3621 | N9: 277.8082 | O9: N | P9: SN-50005 | Q9: New acquisition
A10: 7 | B10: 2023 | C10: Industrial Chiller | D10: Industrial Robot | E10: Supplier K | F10: Brazil | G10: 04-Jan-2023 | H10: 10 | I10: 1219945 | J10: 33.06 | K10: 0.00293 | L10: 1.889 | M10: 3.5744 | N10: 62.4503 | O10: Y | P10: SN-50006 | Q10: Expansion
A11: 8 | B11: 2023 | C11: Injection Moulding Press | D11: Forklift | E11: Supplier G | F11: Singapore | G11: 03-Aug-2023 | H11: 19 | I11: 1316403 | J11: 3.94 | K11: 0.00309 | L11: 24.329 | M11: 4.0677 | N11: 95.8563 | O11: N | P11: SN-50007 | Q11: New acquisition
A12: 9 | B12: 2023 | C12: Injection Moulding Press | D12: Manufacturing Equipment | E12: Supplier E | F12: Germany | G12: 13-Nov-2023 | H12: 6 | I12: 743256 | J12: 36.22 | K12: 0.00322 | L12: 14.709 | M12: 2.3933 | N12: 532.76 | O12: N | P12: SN-50008 | Q12: New acquisition
A13: 10 | B13: 2023 | C13: Industrial Chiller | D13: Building/Construction | E13: Supplier Q | F13: USA | G13: 26-Jun-2023 | H13: 18 | I13: 547845 | J13: 33.27 | K13: 0.0022 | L13: 11.721 | M13: 1.2053 | N13: 389.9577 | O13: Y | P13: SN-50009 | Q13: Replacement
A14: 11 | B14: 2023 | C14: Warehouse Extension | D14: Solar PV Installation | E14: Supplier T | F14: India | G14: 04-Jan-2023 | H14: 11 | I14: 1358045 | J14: 29.86 | K14: 0.00234 | L14: 8.54 | M14: 3.1778 | N14: 255.0044 | O14: N | P14: SN-50010 | Q14: New acquisition
A15: 12 | B15: 2023 | C15: Air Compressor | D15: Solar PV Installation | E15: Supplier F | F15: Germany | G15: 14-Jul-2023 | H15: 22 | I15: 1535862 | J15: 38.33 | K15: 0.00151 | L15: 4.056 | M15: 2.3192 | N15: 155.4665 | O15: N | P15: SN-50011 | Q15: New acquisition
... A103: 100 | B103: 2023 | C103: Assembly Robot | D103: Forklift | E103: Supplier K | F103: Canada | G103: 02-Aug-2023 | H103: 18 | I103: 1113922 | J103: 2.82 | K103: 0.00171 | L103: 16.511 | M103: 1.9048 | N103: 46.561 | O103: Y | P103: SN-50099 | Q103: Replacement

Sheet Cat 3 – Fuel- and Energy-Rel
A1: Scope 3 – Category 3: Fuel- and Energy-Related Activities
A2: GHG Protocol Corporate Value Chain (Scope 3) Accounting and Reporting Standard | Practice Dataset – 100 Rows
A3: Row # | B3: Reporting Year | C3: Quarter | D3: Facility Name | E3: Country | F3: Energy Type | G3: Fuel/Energy Source | H3: Quantity Consumed | I3: Unit | J3: Upstream EF – Extraction & Processing (kg CO₂e/unit) | K3: T&D Loss Factor (%) | L3: Grid EF (kg CO₂e/kWh) | M3: Upstream Emissions (tCO₂e) | N3: T&D Loss Emissions (tCO₂e) | O3: Total Cat 3 Emissions (tCO₂e) | P3: Data Source | Q3: Notes
A4: 1 | B4: 2023 | C4: Q1 | D4: Facility-D | E4: Netherlands | F4: Steam (purchased) | G4: Heat | H4: 18469.5 | I4: kWh | J4: 0.2807 | K4: 0 | L4: 0 | M4: 5.1844 | N4: 0 | O4: 5.1844 | P4: IEA / IPCC AR6 | Q4: Utility bill
A5: 2 | B5: 2023 | C5: Q2 | D5: Facility-H | E5: Mexico | F5: LPG | G5: Fossil Fuel | H5: 85768.4 | I5: GJ | J5: 0.1917 | K5: 0 | L5: 0 | M5: 16.4418 | N5: 0 | O5: 16.4418 | P5: IEA / IPCC AR6 | Q5: Utility bill
A6: 3 | B6: 2023 | C6: Q3 | D6: Facility-C | E6: Singapore | F6: Steam (purchased) | G6: Heat | H6: 96781.8 | I6: kWh | J6: 0.2836 | K6: 0 | L6: 0 | M6: 27.4473 | N6: 0 | O6: 27.4473 | P6: IEA / IPCC AR6 | Q6: Utility bill
A7: 4 | B7: 2023 | C7: Q4 | D7: Facility-H | E7: Netherlands | F7: LPG | G7: Fossil Fuel | H7: 20413.3 | I7: GJ | J7: 0.267 | K7: 0 | L7: 0 | M7: 5.4504 | N7: 0 | O7: 5.4504 | P7: IEA / IPCC AR6 | Q7: Meter reading
A8: 5 | B8: 2023 | C8: Q1 | D8: Facility-A | E8: China | F8: Natural Gas | G8: Fossil Fuel | H8: 53610 | I8: GJ | J8: 0.4544 | K8: 0 | L8: 0 | M8: 24.3604 | N8: 0 | O8: 24.3604 | P8: IEA / IPCC AR6 | Q8: Meter reading
A9: 6 | B9: 2023 | C9: Q2 | D9: Facility-D | E9: Japan | F9: Electricity | G9: Grid | H9: 87374.7 | I9: kWh | J9: 0.3982 | K9: 6.57 | L9: 0.7122 | M9: 34.7926 | N9: 4.0884 | O9: 38.881 | P9: IEA / IPCC AR6 | Q9: Utility bill
A10: 7 | B10: 2023 | C10: Q3 | D10: Facility-D | E10: Mexico | F10: Fuel Oil | G10: Fossil Fuel | H10: 30388.5 | I10: GJ | J10: 0.6163 | K10: 0 | L10: 0 | M10: 18.7284 | N10: 0 | O10: 18.7284 | P10: IEA / IPCC AR6 | Q10: Utility bill
A11: 8 | B11: 2023 | C11: Q4 | D11: Facility-D | E11: Canada | F11: Natural Gas | G11: Fossil Fuel | H11: 74713.2 | I11: GJ | J11: 0.4431 | K11: 0 | L11: 0 | M11: 33.1054 | N11: 0 | O11: 33.1054 | P11: IEA / IPCC AR6 | Q11: Estimate
A12: 9 | B12: 2023 | C12: Q1 | D12: Facility-F | E12: South Korea | F12: Coal | G12: Fossil Fuel | H12: 39723.5 | I12: GJ | J12: 0.3859 | K12: 0 | L12: 0 | M12: 15.3293 | N12: 0 | O12: 15.3293 | P12: IEA / IPCC AR6 | Q12: Meter reading
A13: 10 | B13: 2023 | C13: Q2 | D13: Facility-E | E13: China | F13: Steam (purchased) | G13: Heat | H13: 46678.4 | I13: kWh | J13: 0.2973 | K13: 0 | L13: 0 | M13: 13.8775 | N13: 0 | O13: 13.8775 | P13: IEA / IPCC AR6 | Q13: Meter reading
A14: 11 | B14: 2023 | C14: Q3 | D14: Facility-H | E14: South Korea | F14: Biomass Pellets | G14: Renewable | H14: 46653.8 | I14: GJ | J14: 0.1004 | K14: 0 | L14: 0 | M14: 4.684 | N14: 0 | O14: 4.684 | P14: IEA / IPCC AR6 | Q14: Meter reading
A15: 12 | B15: 2023 | C15: Q4 | D15: Facility-D | E15: Canada | F15: Coal | G15: Fossil Fuel | H15: 37133.4 | I15: GJ | J15: 0.4121 | K15: 0 | L15: 0 | M15: 15.3027 | N15: 0 | O15: 15.3027 | P15: IEA / IPCC AR6 | Q15: Utility bill
... A103: 100 | B103: 2023 | C103: Q4 | D103: Facility-H | E103: USA | F103: Natural Gas | G103: Fossil Fuel | H103: 70399.4 | I103: GJ | J103: 0.3302 | K103: 0 | L103: 0 | M103: 23.2459 | N103: 0 | O103: 23.2459 | P103: IEA / IPCC AR6 | Q103: Utility bill

Sheet Cat 4 – Upstream Transportat
A1: Scope 3 – Category 4: Upstream Transportation & Distribution
A2: GHG Protocol Corporate Value Chain (Scope 3) Accounting and Reporting Standard | Practice Dataset – 100 Rows
A3: Row # | B3: Reporting Year | C3: Quarter | D3: Shipment ID | E3: Origin Country | F3: Destination Country | G3: Supplier Name | H3: Product Category | I3: Transport Mode | J3: Carrier Name | K3: Mass Shipped (tonne) | L3: Distance (km) | M3: Tonne-km | N3: Emission Factor (kg CO₂e/tonne-km) | O3: Emissions (tCO₂e) | P3: Freight Spend (USD) | Q3: Spend-Based EF (kg CO₂e/USD) | R3: Emissions – Spend Method (tCO₂e) | S3: Calculation Method | T3: Data Quality
A4: 1 | B4: 2023 | C4: Q1 | D4: SHP-20000 | E4: Netherlands | F4: USA | G4: Supplier N | H4: Adhesive Tape | I4: Inland Waterway | J4: Maersk | K4: 113.48 | L4: 10215.7 | M4: 1159277.6 | N4: 0.033 | O4: 38.25616 | P4: 331.24 | Q4: 0.00151 | R4: 0.0005 | S4: Spend-based | T4: Primary – carrier data
A5: 2 | B5: 2023 | C5: Q2 | D5: SHP-20001 | E5: Mexico | F5: China | G5: Supplier E | H5: Cotton Fabric | I5: Rail | J5: Maersk | K5: 191.84 | L5: 10974.9 | M5: 2105424.8 | N5: 0.028 | O5: 58.95189 | P5: 2650.44 | Q5: 0.0009 | R5: 0.00239 | S5: Distance-based | T5: Primary – carrier data
A6: 3 | B6: 2023 | C6: Q3 | D6: SHP-20002 | E6: UK | F6: France | G6: Supplier E | H6: Carbon Fibre | I6: Inland Waterway | J6: Kuehne+Nagel | K6: 281.86 | L6: 9174.3 | M6: 2585868.2 | N6: 0.033 | O6: 85.33365 | P6: 4186.5 | Q6: 0.00096 | R6: 0.00402 | S6: Spend-based | T6: Primary – carrier data
A7: 4 | B7: 2023 | C7: Q4 | D7: SHP-20003 | E7: Brazil | F7: Singapore | G7: Supplier K | H7: Lubricant Oil | I7: Road | J7: Maersk | K7: 448.35 | L7: 2143.2 | M7: 960903.72 | N7: 0.1 | O7: 96.09037 | P7: 3166.61 | Q7: 0.00157 | R7: 0.00497 | S7: Distance-based | T7: Secondary – GLEC default
A8: 5 | B8: 2023 | C8: Q1 | D8: SHP-20004 | E8: South Korea | F8: Canada | G8: Supplier A | H8: Ceramic Tiles | I8: Road (refrigerated) | J8: UPS | K8: 42.58 | L8: 8323.3 | M8: 354406.11 | N8: 0.18 | O8: 63.7931 | P8: 15040.2 | Q8: 0.00137 | R8: 0.02061 | S8: Distance-based | T8: Estimate
A9: 6 | B9: 2023 | C9: Q2 | D9: SHP-20005 | E9: Mexico | F9: South Korea | G9: Supplier H | H9: Paper Rolls | I9: Inland Waterway | J9: Kuehne+Nagel | K9: 255.01 | L9: 11230.3 | M9: 2863838.8 | N9: 0.033 | O9: 94.50668 | P9: 7459 | Q9: 0.00049 | R9: 0.00365 | S9: Distance-based | T9: Primary – carrier data
A10: 7 | B10: 2023 | C10: Q3 | D10: SHP-20006 | E10: Brazil | F10: Mexico | G10: Supplier K | H10: Copper Wire | I10: Air | J10: Kuehne+Nagel | K10: 319.22 | L10: 1111.6 | M10: 354844.95 | N10: 0.95 | O10: 337.1027 | P10: 22229.24 | Q10: 0.00042 | R10: 0.00934 | S10: Spend-based | T10: Secondary – GLEC default
A11: 8 | B11: 2023 | C11: Q4 | D11: SHP-20007 | E11: India | F11: UAE | G11: Supplier C | H11: Steel Sheets | I11: Inland Waterway | J11: UPS | K11: 341.63 | L11: 11452.8 | M11: 3912620.1 | N11: 0.033 | O11: 129.11646 | P11: 23865.88 | Q11: 0.00163 | R11: 0.0389 | S11: Distance-based | T11: Primary – carrier data
A12: 9 | B12: 2023 | C12: Q1 | D12: SHP-20008 | E12: South Korea | F12: Singapore | G12: Supplier N | H12: Adhesive Tape | I12: Road | J12: Kuehne+Nagel | K12: 474.37 | L12: 5999.7 | M12: 2846077.7 | N12: 0.1 | O12: 284.60777 | P12: 7233.55 | Q12: 0.00154 | R12: 0.01114 | S12: Distance-based | T12: Estimate
A13: 10 | B13: 2023 | C13: Q2 | D13: SHP-20009 | E13: Mexico | F13: UK | G13: Supplier E | H13: Chemical Solvent | I13: Inland Waterway | J13: CEVA | K13: 269.06 | L13: 2332.6 | M13: 627609.36 | N13: 0.033 | O13: 20.71111 | P13: 2181.57 | Q13: 0.00053 | R13: 0.00116 | S13: Spend-based | T13: Estimate
A14: 11 | B14: 2023 | C14: Q3 | D14: SHP-20010 | E14: Singapore | F14: Canada | G14: Supplier H | H14: Steel Sheets | I14: Road (refrigerated) | J14: DB Schenker | K14: 381.73 | L14: 9765.1 | M14: 3727631.6 | N14: 0.18 | O14: 670.97369 | P14: 16114.55 | Q14: 0.0009 | R14: 0.0145 | S14: Distance-based | T14: Secondary – GLEC default
A15: 12 | B15: 2023 | C15: Q4 | D15: SHP-20011 | E15: Canada | F15: Germany | G15: Supplier D | H15: Steel Sheets | I15: Road | J15: Maersk | K15: 226.96 | L15: 9152 | M15: 2077137.9 | N15: 0.1 | O15: 207.71379 | P15: 7801.32 | Q15: 0.00159 | R15: 0.0124 | S15: Distance-based | T15: Primary – carrier data
... A103: 100 | B103: 2023 | C103: Q4 | D103: SHP-20099 | E103: France | F103: China | G103: Supplier Q | H103: Chemical Solvent | I103: Inland Waterway | J103: DB Schenker | K103: 274.77 | L103: 12397.3 | M103: 3406406.1 | N103: 0.033 | O103: 112.4114 | P103: 19815.4 | Q103: 0.00194 | R103: 0.03844 | S103: Spend-based | T103: Secondary – GLEC default

Sheet Cat 5 – Waste Generated in O
A1: Scope 3 – Category 5: Waste Generated in Operations
A2: GHG Protocol Corporate Value Chain (Scope 3) Accounting and Reporting Standard | Practice Dataset – 100 Rows
A3: Row # | B3: Reporting Year | C3: Quarter | D3: Facility Name | E3: Country | F3: Waste Stream | G3: Waste Composition | H3: Mass Generated (tonne) | I3: Disposal Route | J3: Contractor Name | K3: Emission Factor (kg CO₂e/tonne) | L3: Emissions (tCO₂e) | M3: Waste Diverted from Landfill (tonne) | N3: Diversion Rate (%) | O3: Cost of Disposal (USD) | P3: Data Source | Q3: Notes
A4: 1 | B4: 2023 | C4: Q1 | D4: Plant-E | E4: UAE | F4: Food/Organic Waste | G4: Food/Organic Waste | H4: 2.808 | I4: Secure Chemical Disposal | J4: WM Environmental | K4: 0.5469 | L4: 0.00154 | M4: 1.149 | N4: 40.9 | O4: 2822.75 | P4: IPCC Waste / US EPA WARM | Q4: Estimate
A5: 2 | B5: 2023 | C5: Q2 | D5: Plant-C | E5: Netherlands | F5: Food/Organic Waste | G5: Food/Organic Waste | H5: 22.681 | I5: Energy Recovery | J5: Republic Services | K5: 0.5092 | L5: 0.01155 | M5: 13.45 | N5: 59.3 | O5: 60.87 | P5: IPCC Waste / US EPA WARM | Q5: Estimate
A6: 3 | B6: 2023 | C6: Q3 | D6: Plant-F | E6: Canada | F6: Wastewater (industrial) | G6: Wastewater (industrial) | H6: 35.135 | I6: Recycling | J6: Renewi | K6: 0.0658 | L6: 0.00176 | M6: 5.191 | N6: 14.8 | O6: 745.22 | P6: IPCC Waste / US EPA WARM | Q6: Waste manifest
A7: 4 | B7: 2023 | C7: Q4 | D7: Plant-B | E7: Canada | F7: Plastic Waste | G7: Plastic Waste | H7: 9.876 | I7: Anaerobic Digestion | J7: Biffa | K7: 0.7743 | L7: 0.00765 | M7: 7.575 | N7: 76.7 | O7: 1117.17 | P7: IPCC Waste / US EPA WARM | Q7: Waste manifest
A8: 5 | B8: 2023 | C8: Q1 | D8: Plant-D | E8: Japan | F8: Electronic Waste (WEEE) | G8: Electronic Waste (WEEE) | H8: 46.339 | I8: Landfill | J8: Remondis | K8: 0.3047 | L8: 0.01412 | M8: 0 | N8: 0 | O8: 2964.61 | P8: IPCC Waste / US EPA WARM | Q8: Estimate
A9: 6 | B9: 2023 | C9: Q2 | D9: Plant-E | E9: Japan | F9: Metal Scrap | G9: Metal Scrap | H9: 0.316 | I9: Composting | J9: Covanta | K9: 0.0467 | L9: 1e-05 | M9: 0.157 | N9: 49.7 | O9: 2192.41 | P9: IPCC Waste / US EPA WARM | Q9: Waste manifest
A10: 7 | B10: 2023 | C10: Q3 | D10: Plant-C | E10: Australia | F10: Rubber | G10: Rubber | H10: 36.552 | I10: Incineration | J10: Renewi | K10: 0.6049 | L10: 0.02211 | M10: 12.744 | N10: 34.9 | O10: 3022.7 | P10: IPCC Waste / US EPA WARM | Q10: Contractor invoice
A11: 8 | B11: 2023 | C11: Q4 | D11: Plant-D | E11: South Korea | F11: Rubber | G11: Rubber | H11: 38.142 | I11: Energy Recovery | J11: Clean Harbors | K11: 0.6558 | L11: 0.02501 | M11: 33.078 | N11: 86.7 | O11: 4853.93 | P11: IPCC Waste / US EPA WARM | Q11: Waste manifest
A12: 9 | B12: 2023 | C12: Q1 | D12: Plant-C | E12: Canada | F12: Electronic Waste (WEEE) | G12: Electronic Waste (WEEE) | H12: 35.031 | I12: Anaerobic Digestion | J12: Covanta | K12: 0.2936 | L12: 0.01029 | M12: 9.424 | N12: 26.9 | O12: 3522.4 | P12: IPCC Waste / US EPA WARM | Q12: Estimate
A13: 10 | B13: 2023 | C13: Q2 | D13: Plant-B | E13: Canada | F13: Paper & Cardboard | G13: Paper & Cardboard | H13: 10.565 | I13: Incineration | J13: Clean Harbors | K13: 0.4397 | L13: 0.00465 | M13: 6.529 | N13: 61.8 | O13: 4609.9 | P13: IPCC Waste / US EPA WARM | Q13: Estimate
A14: 11 | B14: 2023 | C14: Q3 | D14: Plant-E | E14: UAE | F14: Wastewater (industrial) | G14: Wastewater (industrial) | H14: 31.88 | I14: Energy Recovery | J14: Renewi | K14: 0.0924 | L14: 0.00295 | M14: 21.828 | N14: 68.5 | O14: 2833.29 | P14: IPCC Waste / US EPA WARM | Q14: Estimate
A15: 12 | B15: 2023 | C15: Q4 | D15: Plant-D | E15: Germany | F15: Wastewater (industrial) | G15: Wastewater (industrial) | H15: 43.886 | I15: Recycling | J15: Veolia | K15: 0.0809 | L15: 0.00219 | M15: 0.504 | N15: 1.1 | O15: 577.03 | P15: IPCC Waste / US EPA WARM | Q15: Estimate
... A103: 100 | B103: 2023 | C103: Q4 | D103: Plant-D | E103: China | F103: Hazardous Chemical Waste | G103: Hazardous Chemical Waste | H103: 13.196 | I103: Landfill | J103: Stericycle | K103: 1.0532 | L103: 0.0139 | M103: 0 | N103: 0 | O103: 3291.42 | P103: IPCC Waste / US EPA WARM | Q103: Waste manifest

Sheet Cat 6 – Business Travel
A1: Scope 3 – Category 6: Business Travel
A2: GHG Protocol Corporate Value Chain (Scope 3) Accounting and Reporting Standard | Practice Dataset – 100 Rows
A3: Row # | B3: Reporting Year | C3: Quarter | D3: Employee ID | E3: Department | F3: Travel Type | G3: Origin City | H3: Destination City | I3: Transport Mode | J3: Travel Class | K3: Distance (km) | L3: Radiative Forcing Included (Y/N) | M3: Emission Factor (kg CO₂e/pkm) | N3: Emissions from Travel (tCO₂e) | O3: Hotel Nights | P3: Hotel EF (kg CO₂e/night) | Q3: Hotel Emissions (tCO₂e) | R3: Total Trip Emissions (tCO₂e) | S3: Trip Purpose | T3: Booking Channel
A4: 1 | B4: 2023 | C4: Q1 | D4: EMP-3000 | E4: Sales | F4: International | G4: Mumbai | H4: Mumbai | I4: Rail | J4: Economy | K4: 5345.8 | L4: N | M4: 0.041 | N4: 0.21918 | O4: 2 | P4: 18.28 | Q4: 0.03656 | R4: 0.25574 | S4: Supplier Visit | T4: Direct Booking
A5: 2 | B5: 2023 | C5: Q2 | D5: EMP-3001 | E5: Sales | F5: International | G5: Amsterdam | H5: Paris | I5: Bus | J5: Economy | K5: 11701 | L5: Y | M5: 0.089 | N5: 1.04139 | O5: 4 | P5: 28.71 | Q5: 0.11484 | R5: 1.15623 | S5: Board Meeting | T5: Travel Agent
A6: 3 | B6: 2023 | C6: Q3 | D6: EMP-3002 | E6: Marketing | F6: International | G6: Paris | H6: Singapore | I6: Car – Electric | J6: N/A | K6: 6305.3 | L6: Y | M6: 0.062 | N6: 0.39093 | O6: 4 | P6: 37.72 | Q6: 0.15088 | R6: 0.54181 | S6: Board Meeting | T6: Direct Booking
A7: 4 | B7: 2023 | C7: Q4 | D7: EMP-3003 | E7: Finance | F7: International | G7: Paris | H7: Nairobi | I7: Car – Petrol | J7: N/A | K7: 4975.8 | L7: Y | M7: 0.192 | N7: 0.95535 | O7: 2 | P7: 22.59 | Q7: 0.04518 | R7: 1.00053 | S7: Supplier Visit | T7: Direct Booking
A8: 5 | B8: 2023 | C8: Q1 | D8: EMP-3004 | E8: Marketing | F8: International | G8: Dubai | H8: Mumbai | I8: Bus | J8: Economy | K8: 6444.4 | L8: N | M8: 0.089 | N8: 0.57355 | O8: 7 | P8: 38.67 | Q8: 0.27069 | R8: 0.84424 | S8: Site Audit | T8: Travel Agent
A9: 6 | B9: 2023 | C9: Q2 | D9: EMP-3005 | E9: Legal | F9: International | G9: Sydney | H9: Singapore | I9: Air – Long Haul | J9: Business | K9: 9571.4 | L9: Y | M9: 0.585 | N9: 5.59927 | O9: 5 | P9: 19.71 | Q9: 0.09855 | R9: 5.69782 | S9: Trade Show | T9: Direct Booking
A10: 7 | B10: 2023 | C10: Q3 | D10: EMP-3006 | E10: HR | F10: International | G10: Dubai | H10: Seoul | I10: Air – Long Haul | J10: Business | K10: 3192.6 | L10: N | M10: 0.585 | N10: 1.86767 | O10: 6 | P10: 30.63 | Q10: 0.18378 | R10: 2.05145 | S10: Trade Show | T10: Corporate Travel Portal
A11: 8 | B11: 2023 | C11: Q4 | D11: EMP-3007 | E11: Marketing | F11: International | G11: Toronto | H11: Tokyo | I11: Air – Short Haul | J11: Business | K11: 2229.8 | L11: N | M11: 0.51 | N11: 1.1372 | O11: 4 | P11: 17.76 | Q11: 0.07104 | R11: 1.20824 | S11: Board Meeting | T11: Corporate Travel Portal
A12: 9 | B12: 2023 | C12: Q1 | D12: EMP-3008 | E12: Finance | F12: Domestic | G12: New York | H12: London | I12: Car – Petrol | J12: N/A | K12: 281.8 | L12: N | M12: 0.192 | N12: 0.05411 | O12: 0 | P12: 39.24 | Q12: 0 | R12: 0.05411 | S12: Site Audit | T12: Corporate Travel Portal
A13: 10 | B13: 2023 | C13: Q2 | D13: EMP-3009 | E13: Finance | F13: International | G13: Tokyo | H13: Singapore | I13: Bus | J13: Economy | K13: 8738.9 | L13: N | M13: 0.089 | N13: 0.77776 | O13: 3 | P13: 17.25 | Q13: 0.05175 | R13: 0.82951 | S13: Trade Show | T13: Direct Booking
A14: 11 | B14: 2023 | C14: Q3 | D14: EMP-3010 | E14: Finance | F14: International | G14: Frankfurt | H14: London | I14: Bus | J14: Economy | K14: 11975.7 | L14: Y | M14: 0.089 | N14: 1.06584 | O14: 7 | P14: 32.42 | Q14: 0.22694 | R14: 1.29278 | S14: Client Meeting | T14: Direct Booking
A15: 12 | B15: 2023 | C15: Q4 | D15: EMP-3011 | E15: HR | F15: Domestic | G15: Nairobi | H15: Sydney | I15: Car – Electric | J15: N/A | K15: 903 | L15: Y | M15: 0.062 | N15: 0.05599 | O15: 7 | P15: 19.54 | Q15: 0.13678 | R15: 0.19277 | S15: Conference | T15: Travel Agent
... A103: 100 | B103: 2023 | C103: Q4 | D103: EMP-3099 | E103: R&D | F103: International | G103: Amsterdam | H103: Shanghai | I103: Bus | J103: Economy | K103: 7415 | L103: Y | M103: 0.089 | N103: 0.65993 | O103: 4 | P103: 23.31 | Q103: 0.09324 | R103: 0.75317 | S103: Board Meeting | T103: Travel Agent

Sheet Cat 7 – Employee Commuting
A1: Scope 3 – Category 7: Employee Commuting
A2: GHG Protocol Corporate Value Chain (Scope 3) Accounting and Reporting Standard | Practice Dataset – 100 Rows
A3: Row # | B3: Reporting Year | C3: Quarter | D3: Employee ID | E3: Department | F3: Work Location | G3: Country | H3: Commute Mode | I3: Weekly Commute Days | J3: One-Way Distance (km) | K3: Annual Working Weeks | L3: Annual Commute Distance (km) | M3: Emission Factor (kg CO₂e/km) | N3: Annual Emissions (tCO₂e) | O3: WFH Days per Week | P3: WFH Energy Consumption (kWh/day) | Q3: WFH Grid EF (kg CO₂e/kWh) | R3: WFH Annual Emissions (tCO₂e) | S3: Total Annual Emissions (tCO₂e) | T3: Data Source
A4: 1 | B4: 2023 | C4: Q1 | D4: EMP-5000 | E4: IT | F4: Warehouse | G4: France | H4: Electric Vehicle | I4: 1 | J4: 49.1 | K4: 49 | L4: 4811.8 | M4: 0.062 | N4: 0.29833 | O4: 3 | P4: 2.58 | Q4: 0.4959 | R4: 0.18808 | S4: 0.48641 | T4: Employee survey
A5: 2 | B5: 2023 | C5: Q2 | D5: EMP-5001 | E5: Procurement | F5: Manufacturing Plant | G5: Canada | H5: Motorcycle | I5: 2 | J5: 51.9 | K5: 48 | L5: 9964.8 | M5: 0.113 | N5: 1.12602 | O5: 2 | P5: 7.48 | Q5: 0.5343 | R5: 0.38367 | S5: 1.50969 | T5: HR payroll data
A6: 3 | B6: 2023 | C6: Q3 | D6: EMP-5002 | E6: Procurement | F6: R&D Centre | G6: China | H6: Walking | I6: 1 | J6: 5.8 | K6: 44 | L6: 510.4 | M6: 0 | N6: 0 | O6: 2 | P6: 4.87 | Q6: 0.7475 | R6: 0.32035 | S6: 0.32035 | T6: Estimated
A7: 4 | B7: 2023 | C7: Q4 | D7: EMP-5003 | E7: HR | F7: R&D Centre | G7: South Korea | H7: Electric Vehicle | I7: 5 | J7: 8 | K7: 50 | L7: 4000 | M7: 0.062 | N7: 0.248 | O7: 0 | P7: 3.96 | Q7: 0.6552 | R7: 0 | S7: 0.248 | T7: HR payroll data
A8: 5 | B8: 2023 | C8: Q1 | D8: EMP-5004 | E8: Operations | F8: Manufacturing Plant | G8: Singapore | H8: Cycle | I8: 5 | J8: 26 | K8: 48 | L8: 12480 | M8: 0 | N8: 0 | O8: 1 | P8: 5.29 | Q8: 0.8077 | R8: 0.20509 | S8: 0.20509 | T8: Employee survey
A9: 6 | B9: 2023 | C9: Q2 | D9: EMP-5005 | E9: Operations | F9: R&D Centre | G9: France | H9: Cycle | I9: 4 | J9: 34.9 | K9: 46 | L9: 12843.2 | M9: 0 | N9: 0 | O9: 4 | P9: 6.16 | Q9: 0.4314 | R9: 0.48897 | S9: 0.48897 | T9: HR payroll data
A10: 7 | B10: 2023 | C10: Q3 | D10: EMP-5006 | E10: Legal | F10: Head Office | G10: China | H10: Private Car – Diesel | I10: 5 | J10: 36.6 | K10: 46 | L10: 16836 | M10: 0.171 | N10: 2.87896 | O10: 4 | P10: 2.59 | Q10: 0.5593 | R10: 0.26654 | S10: 3.1455 | T10: Estimated
A11: 8 | B11: 2023 | C11: Q4 | D11: EMP-5007 | E11: R&D | F11: Regional Office | G11: USA | H11: Private Car – Diesel | I11: 5 | J11: 46.7 | K11: 47 | L11: 21949 | M11: 0.171 | N11: 3.75328 | O11: 2 | P11: 4.97 | Q11: 0.6603 | R11: 0.30848 | S11: 4.06176 | T11: Estimated
A12: 9 | B12: 2023 | C12: Q1 | D12: EMP-5008 | E12: R&D | F12: Regional Office | G12: Japan | H12: Private Car – Petrol | I12: 2 | J12: 40.3 | K12: 47 | L12: 7576.4 | M12: 0.192 | N12: 1.45467 | O12: 4 | P12: 3.75 | Q12: 0.6393 | R12: 0.45071 | S12: 1.90538 | T12: Estimated
A13: 10 | B13: 2023 | C13: Q2 | D13: EMP-5009 | E13: Procurement | F13: Head Office | G13: Canada | H13: Metro / Suburban Rail | I13: 3 | J13: 35.1 | K13: 49 | L13: 10319.4 | M13: 0.041 | N13: 0.4231 | O13: 2 | P13: 7.51 | Q13: 0.7902 | R13: 0.58157 | S13: 1.00467 | T13: Estimated
A14: 11 | B14: 2023 | C14: Q3 | D14: EMP-5010 | E14: Manufacturing | F14: Head Office | G14: Mexico | H14: Private Car – Petrol | I14: 5 | J14: 59.2 | K14: 47 | L14: 27824 | M14: 0.192 | N14: 5.34221 | O14: 1 | P14: 7.12 | Q14: 0.3793 | R14: 0.12693 | S14: 5.46914 | T14: Employee survey
A15: 12 | B15: 2023 | C15: Q4 | D15: EMP-5011 | E15: Procurement | F15: Warehouse | G15: Singapore | H15: Carpool | I15: 3 | J15: 8.4 | K15: 46 | L15: 2318.4 | M15: 0.096 | N15: 0.22257 | O15: 0 | P15: 3.41 | Q15: 0.68 | R15: 0 | S15: 0.22257 | T15: HR payroll data
... A103: 100 | B103: 2023 | C103: Q4 | D103: EMP-5099 | E103: Procurement | F103: Manufacturing Plant | G103: Japan | H103: Private Car – Diesel | I103: 4 | J103: 28.7 | K103: 44 | L103: 10102.4 | M103: 0.171 | N103: 1.72751 | O103: 0 | P103: 6.91 | Q103: 0.784 | R103: 0 | S103: 1.72751 | T103: Estimated

Sheet Cat 8 – Upstream Leased Asse
A1: Scope 3 – Category 8: Upstream Leased Assets
A2: GHG Protocol Corporate Value Chain (Scope 3) Accounting and Reporting Standard | Practice Dataset – 100 Rows
A3: Row # | B3: Reporting Year | C3: Quarter | D3: Asset ID | E3: Asset Type | F3: Lessor Name | G3: Country | H3: Lease Start Date | I3: Lease End Date | J3: Floor Area / Capacity | K3: Unit | L3: Energy Consumed (kWh) | M3: Fuel Consumed (GJ) | N3: Grid EF – Electricity (kg CO₂e/kWh) | O3: Fuel EF (kg CO₂e/GJ) | P3: Elec Emissions (tCO₂e) | Q3: Fuel Emissions (tCO₂e) | R3: Total Emissions (tCO₂e) | S3: Annual Lease Cost (USD) | T3: Data Quality
A4: 1 | B4: 2023 | C4: Q1 | D4: LA-6000 | E4: Car Park | F4: JLL Property | G4: UK | H4: 01-Jan-2019 | I4: 31-Dec-2029 | J4: 738.1 | K4: m² | L4: 221527 | M4: 197.52 | N4: 0.6116 | O4: 79.1 | P4: 135.4859 | Q4: 15.6238 | R4: 151.1097 | S4: 159295 | T4: Lessor-reported
A5: 2 | B5: 2023 | C5: Q2 | D5: LA-6001 | E5: Warehouse | F5: Savills | G5: South Korea | H5: 01-Jan-2018 | I5: 31-Dec-2024 | J5: 3455.8 | K5: m² | L5: 154406.7 | M5: 41.97 | N5: 0.8406 | O5: 62.74 | P5: 129.7943 | Q5: 2.6332 | R5: 132.4275 | S5: 19215 | T5: Meter reading
A6: 3 | B6: 2023 | C6: Q3 | D6: LA-6002 | E6: Office Space | F6: CBRE GWS | G6: South Korea | H6: 01-Jan-2020 | I6: 31-Dec-2024 | J6: 1021.9 | K6: m² | L6: 17363.6 | M6: 131.96 | N6: 0.6466 | O6: 64.07 | P6: 11.2273 | Q6: 8.4547 | R6: 19.682 | S6: 42461 | T6: Lessor-reported
A7: 4 | B7: 2023 | C7: Q4 | D7: LA-6003 | E7: Retail Unit | F7: Segro | G7: UAE | H7: 01-Jan-2018 | I7: 31-Dec-2025 | J7: 4604.5 | K7: m² | L7: 103495.2 | M7: 180.23 | N7: 0.4424 | O7: 60.55 | P7: 45.7863 | Q7: 10.9129 | R7: 56.6992 | S7: 424472 | T7: Meter reading
A8: 5 | B8: 2023 | C8: Q1 | D8: LA-6004 | E8: Car Park | F8: CBRE GWS | G8: Australia | H8: 01-Jan-2018 | I8: 31-Dec-2030 | J8: 844.8 | K8: m² | L8: 250816.6 | M8: 145.71 | N8: 0.4709 | O8: 67.11 | P8: 118.1095 | Q8: 9.7786 | R8: 127.8881 | S8: 293286 | T8: Lessor-reported
A9: 6 | B9: 2023 | C9: Q2 | D9: LA-6005 | E9: Manufacturing Shed | F9: Savills | G9: Brazil | H9: 01-Jan-2019 | I9: 31-Dec-2028 | J9: 4823.1 | K9: m² | L9: 86715 | M9: 150.8 | N9: 0.3522 | O9: 71.76 | P9: 30.541 | Q9: 10.8214 | R9: 41.3624 | S9: 427135 | T9: Estimate
A10: 7 | B10: 2023 | C10: Q3 | D10: LA-6006 | E10: Laboratory Space | F10: GLP | G10: USA | H10: 01-Jan-2021 | I10: 31-Dec-2025 | J10: 966.4 | K10: m² | L10: 337089.3 | M10: 21.46 | N10: 0.7674 | O10: 79.44 | P10: 258.6823 | Q10: 1.7048 | R10: 260.3871 | S10: 261983 | T10: Meter reading
A11: 8 | B11: 2023 | C11: Q4 | D11: LA-6007 | E11: Retail Unit | F11: JLL Property | G11: Singapore | H11: 01-Jan-2018 | I11: 31-Dec-2024 | J11: 2356.2 | K11: m² | L11: 260344.1 | M11: 99.16 | N11: 0.5306 | O11: 58.65 | P11: 138.1386 | Q11: 5.8157 | R11: 143.9543 | S11: 170777 | T11: Meter reading
A12: 9 | B12: 2023 | C12: Q1 | D12: LA-6008 | E12: Server Co-Location | F12: JLL Property | G12: Mexico | H12: 01-Jan-2020 | I12: 31-Dec-2030 | J12: 3021.9 | K12: m² | L12: 156691.4 | M12: 195.24 | N12: 0.572 | O12: 66.62 | P12: 89.6275 | Q12: 13.0069 | R12: 102.6344 | S12: 219701 | T12: Meter reading
A13: 10 | B13: 2023 | C13: Q2 | D13: LA-6009 | E13: Car Park | F13: GLP | G13: Canada | H13: 01-Jan-2018 | I13: 31-Dec-2024 | J13: 937.5 | K13: m² | L13: 499362.9 | M13: 98.33 | N13: 0.4026 | O13: 63.14 | P13: 201.0435 | Q13: 6.2086 | R13: 207.2521 | S13: 80250 | T13: Estimate
A14: 11 | B14: 2023 | C14: Q3 | D14: LA-6010 | E14: Retail Unit | F14: GLP | G14: USA | H14: 01-Jan-2019 | I14: 31-Dec-2028 | J14: 3720.1 | K14: m² | L14: 446321.4 | M14: 33.74 | N14: 0.5319 | O14: 55.97 | P14: 237.3984 | Q14: 1.8884 | R14: 239.2868 | S14: 423574 | T14: Lessor-reported
A15: 12 | B15: 2023 | C15: Q4 | D15: LA-6011 | E15: Cold Storage | F15: Colliers | G15: Singapore | H15: 01-Jan-2021 | I15: 31-Dec-2026 | J15: 3639.7 | K15: m² | L15: 139980.6 | M15: 142.7 | N15: 0.641 | O15: 58.19 | P15: 89.7276 | Q15: 8.3037 | R15: 98.0313 | S15: 243155 | T15: Meter reading
... A103: 100 | B103: 2023 | C103: Q4 | D103: LA-6099 | E103: Car Park | F103: Colliers | G103: Germany | H103: 01-Jan-2020 | I103: 31-Dec-2030 | J103: 384.4 | K103: m² | L103: 23296.6 | M103: 96.24 | N103: 0.5049 | O103: 63.57 | P103: 11.7625 | Q103: 6.118 | R103: 17.8805 | S103: 194880 | T103: Lessor-reported

Sheet Cat 9 – Downstream Transport
A1: Scope 3 – Category 9: Downstream Transportation & Distribution
A2: GHG Protocol Corporate Value Chain (Scope 3) Accounting and Reporting Standard | Practice Dataset – 100 Rows
A3: Row # | B3: Reporting Year | C3: Quarter | D3: Shipment ID | E3: Product Category | F3: Origin (Warehouse/DC) | G3: Destination Country | H3: Customer Segment | I3: Transport Mode | J3: 3PL Carrier | K3: Mass Shipped (tonne) | L3: Distance (km) | M3: Tonne-km | N3: EF (kg CO₂e/tonne-km) | O3: Transport Emissions (tCO₂e) | P3: Warehouse Area (m²) | Q3: Warehousing Energy (kWh) | R3: Grid EF (kg CO₂e/kWh) | S3: Warehousing Emissions (tCO₂e) | T3: Total Emissions (tCO₂e)
A4: 1 | B4: 2023 | C4: Q1 | D4: OUT-30000 | E4: Aluminium Ingots | F4: Central Warehouse | G4: France | H4: Government | I4: Last-mile (Van) | J4: GLS | K4: 190.97 | L4: 6098.2 | M4: 1164573.2 | N4: 0.25 | O4: 291.14331 | P4: 3369.4 | Q4: 7874.6 | R4: 0.7139 | S4: 5.62168 | T4: 296.76499
A5: 2 | B5: 2023 | C5: Q2 | D5: OUT-30001 | E5: Adhesive Tape | F5: DC-East | G5: France | H5: B2B Wholesale | I5: Air | J5: UPS | K5: 69.92 | L5: 3175.3 | M5: 222016.98 | N5: 0.8 | O5: 177.61358 | P5: 2750.9 | Q5: 47924.9 | R5: 0.795 | S5: 38.1003 | T5: 215.71388
A6: 3 | B6: 2023 | C6: Q3 | D6: OUT-30002 | E6: Packaging Material | F6: Central Warehouse | G6: USA | H6: B2C E-commerce | I6: Last-mile (Electric Van) | J6: Yodel | K6: 7.54 | L6: 5048.3 | M6: 38064.18 | N6: 0.062 | O6: 2.35998 | P6: 3880.8 | Q6: 15788 | R6: 0.6726 | S6: 10.61901 | T6: 12.97899
A7: 4 | B7: 2023 | C7: Q4 | D7: OUT-30003 | E7: Steel Sheets | F7: DC-North | G7: France | H7: Government | I7: Last-mile (Van) | J7: UPS | K7: 227.31 | L7: 7659.2 | M7: 1741012.8 | N7: 0.25 | O7: 435.25319 | P7: 2656.6 | Q7: 37652.6 | R7: 0.6013 | S7: 22.64051 | T7: 457.8937
A8: 5 | B8: 2023 | C8: Q1 | D8: OUT-30004 | E8: Aluminium Ingots | F8: Central Warehouse | G8: UAE | H8: Retail Partner | I8: Road | J8: GLS | K8: 82.56 | L8: 1662.3 | M8: 137239.49 | N8: 0.1 | O8: 13.72395 | P8: 4165.5 | Q8: 42026.4 | R8: 0.6398 | S8: 26.88849 | T8: 40.61244
A9: 6 | B9: 2023 | C9: Q2 | D9: OUT-30005 | E9: Ceramic Tiles | F9: Central Warehouse | G9: Brazil | H9: Distributor | I9: Last-mile (Van) | J9: XPO | K9: 13.59 | L9: 6898.6 | M9: 93751.97 | N9: 0.25 | O9: 23.43799 | P9: 214 | Q9: 22132.4 | R9: 0.5575 | S9: 12.33881 | T9: 35.7768
A10: 7 | B10: 2023 | C10: Q3 | D10: OUT-30006 | E10: Aluminium Ingots | F10: DC-South | G10: China | H10: Distributor | I10: Road | J10: UPS | K10: 34.48 | L10: 812.7 | M10: 28021.9 | N10: 0.1 | O10: 2.80219 | P10: 924 | Q10: 7629.7 | R10: 0.4778 | S10: 3.64547 | T10: 6.44766
A11: 8 | B11: 2023 | C11: Q4 | D11: OUT-30007 | E11: Rubber Seals | F11: DC-South | G11: Singapore | H11: Retail Partner | I11: Road | J11: XPO | K11: 184.38 | L11: 2615.8 | M11: 482301.2 | N11: 0.1 | O11: 48.23012 | P11: 233.1 | Q11: 3395.8 | R11: 0.545 | S11: 1.85071 | T11: 50.08083
A12: 9 | B12: 2023 | C12: Q1 | D12: OUT-30008 | E12: Plastic Pellets | F12: DC-West | G12: Australia | H12: Government | I12: Air | J12: GLS | K12: 282.48 | L12: 7198 | M12: 2033291 | N12: 0.8 | O12: 1626.6328 | P12: 354.2 | Q12: 12361.3 | R12: 0.6485 | S12: 8.0163 | T12: 1634.6491
A13: 10 | B13: 2023 | C13: Q2 | D13: OUT-30009 | E13: Packaging Material | F13: DC-South | G13: Mexico | H13: B2B Wholesale | I13: Road | J13: XPO | K13: 80.86 | L13: 2560.3 | M13: 207025.86 | N13: 0.1 | O13: 20.70259 | P13: 2810.3 | Q13: 3740.2 | R13: 0.3645 | S13: 1.3633 | T13: 22.06589
A14: 11 | B14: 2023 | C14: Q3 | D14: OUT-30010 | E14: Glass Panels | F14: Central Warehouse | G14: Singapore | H14: Distributor | I14: Last-mile (Van) | J14: FedEx | K14: 289.05 | L14: 5407.3 | M14: 1562980.1 | N14: 0.25 | O14: 390.74502 | P14: 1306.9 | Q14: 27958 | R14: 0.7426 | S14: 20.76161 | T14: 411.50663
A15: 12 | B15: 2023 | C15: Q4 | D15: OUT-30011 | E15: Plastic Pellets | F15: Central Warehouse | G15: Singapore | H15: Government | I15: Last-mile (Electric Van) | J15: Hermes | K15: 150.18 | L15: 6267.4 | M15: 941238.13 | N15: 0.062 | O15: 58.35676 | P15: 797.6 | Q15: 27251.8 | R15: 0.4341 | S15: 11.83001 | T15: 70.18677
... A103: 100 | B103: 2023 | C103: Q4 | D103: OUT-30099 | E103: Adhesive Tape | F103: DC-North | G103: USA | H103: Government | I103: Last-mile (Van) | J103: DPDHL | K103: 197.58 | L103: 3074.7 | M103: 607499.23 | N103: 0.25 | O103: 151.87481 | P103: 1609.1 | Q103: 20874.6 | R103: 0.7882 | S103: 16.45336 | T103: 168.32817

Sheet Cat 10 – Processing of Sold P
A1: Scope 3 – Category 10: Processing of Sold Products
A2: GHG Protocol Corporate Value Chain (Scope 3) Accounting and Reporting Standard | Practice Dataset – 100 Rows
A3: Row # | B3: Reporting Year | C3: Quarter | D3: Customer / Processor | E3: Country | F3: Intermediate Product Sold | G3: Product Description | H3: Mass Sold (tonne) | I3: Processing Type | J3: Energy Required for Processing (GJ/tonne) | K3: Grid EF at Processing Site (kg CO₂e/kWh) | L3: Process EF (kg CO₂e/tonne) | M3: Total Processing Emissions (tCO₂e) | N3: Site-Specific Data (Y/N) | O3: Customer Sector | P3: Notes
A4: 1 | B4: 2023 | C4: Q1 | D4: Supplier M | E4: Canada | F4: Glass Cullet | G4: Intermediate Steel Slab | H4: 814.41 | I4: Extrusion | J4: 4.401 | K4: 0.4548 | L4: 0.556 | M4: 0.4528 | N4: N | O4: Automotive | P4: Customer-reported
A5: 2 | B5: 2023 | C5: Q2 | D5: Supplier J | E5: Canada | F5: Textile Yarn | G5: Intermediate Aluminium Billet | H5: 70.77 | I5: Extrusion | J5: 10.597 | K5: 0.6125 | L5: 1.803 | M5: 0.1276 | N5: N | O5: Electronics | P5: Process engineering estimate
A6: 3 | B6: 2023 | C6: Q3 | D6: Supplier D | E6: Japan | F6: Ceramic Powder | G6: Intermediate Plastic Resin Pellets | H6: 135.2 | I6: Extrusion | J6: 7.554 | K6: 0.6013 | L6: 1.2617 | M6: 0.1706 | N6: Y | O6: Automotive | P6: Process engineering estimate
A7: 4 | B7: 2023 | C7: Q4 | D7: Supplier N | E7: Japan | F7: Ceramic Powder | G7: Intermediate Chemical Precursor | H7: 183.55 | I7: Extrusion | J7: 11.508 | K7: 0.4797 | L7: 1.5335 | M7: 0.2815 | N7: Y | O7: Textiles | P7: Customer-reported
A8: 5 | B8: 2023 | C8: Q1 | D8: Supplier S | E8: UK | F8: Rubber Compound | G8: Intermediate Rubber Compound | H8: 378.35 | I8: Casting | J8: 4.513 | K8: 0.5211 | L8: 0.6533 | M8: 0.2472 | N8: Y | O8: Automotive | P8: Industry average
A9: 6 | B9: 2023 | C9: Q2 | D9: Supplier B | E9: USA | F9: Plastic Resin Pellets | G9: Intermediate Pulp (paper grade) | H9: 752.05 | I9: Moulding | J9: 0.605 | K9: 0.6412 | L9: 0.1078 | M9: 0.0811 | N9: N | O9: Agriculture | P9: Industry average
A10: 7 | B10: 2023 | C10: Q3 | D10: Supplier N | E10: Brazil | F10: Copper Rod | G10: Intermediate Copper Rod | H10: 932.2 | I10: Blending | J10: 7.362 | K10: 0.5185 | L10: 1.0603 | M10: 0.9884 | N10: Y | O10: Consumer Goods | P10: Process engineering estimate
A11: 8 | B11: 2023 | C11: Q4 | D11: Supplier K | E11: South Korea | F11: Chemical Precursor | G11: Intermediate Steel Slab | H11: 399.07 | I11: Sintering | J11: 9.357 | K11: 0.8377 | L11: 2.1773 | M11: 0.8689 | N11: N | O11: Aerospace | P11: Process engineering estimate
A12: 9 | B12: 2023 | C12: Q1 | D12: Supplier D | E12: Netherlands | F12: Pulp (paper grade) | G12: Intermediate Glass Cullet | H12: 835.59 | I12: Weaving | J12: 13.913 | K12: 0.3628 | L12: 1.4021 | M12: 1.1716 | N12: N | O12: Medical Devices | P12: Process engineering estimate
A13: 10 | B13: 2023 | C13: Q2 | D13: Supplier G | E13: India | F13: Copper Rod | G13: Intermediate Steel Slab | H13: 686.5 | I13: Blending | J13: 13.113 | K13: 0.6075 | L13: 2.2128 | M13: 1.5191 | N13: Y | O13: Consumer Goods | P13: Process engineering estimate
A14: 11 | B14: 2023 | C14: Q3 | D14: Supplier T | E14: South Korea | F14: Chemical Precursor | G14: Intermediate Copper Rod | H14: 444.86 | I14: Calendering | J14: 9.298 | K14: 0.5501 | L14: 1.4208 | M14: 0.6321 | N14: N | O14: Construction | P14: Process engineering estimate
A15: 12 | B15: 2023 | C15: Q4 | D15: Supplier Q | E15: Mexico | F15: Ceramic Powder | G15: Intermediate Pulp (paper grade) | H15: 385.47 | I15: Moulding | J15: 9.304 | K15: 0.706 | L15: 1.8246 | M15: 0.7033 | N15: Y | O15: Medical Devices | P15: Customer-reported
... A103: 100 | B103: 2023 | C103: Q4 | D103: Supplier P | E103: Germany | F103: Chemical Precursor | G103: Intermediate Steel Slab | H103: 204.08 | I103: Blending | J103: 12.834 | K103: 0.5312 | L103: 1.8937 | M103: 0.3865 | N103: N | O103: Electronics | P103: Industry average

Sheet Cat 11 – Use of Sold Products
A1: Scope 3 – Category 11: Use of Sold Products
A2: GHG Protocol Corporate Value Chain (Scope 3) Accounting and Reporting Standard | Practice Dataset – 100 Rows
A3: Row # | B3: Reporting Year | C3: Product Category | D3: Product Model / SKU | E3: Units Sold | F3: Product Lifetime (Years) | G3: Annual Energy Use (kWh/unit/yr) | H3: Lifetime Energy Use (kWh/unit) | I3: Fuel Consumed per Unit (L/yr) | J3: Fuel Type | K3: Grid EF (kg CO₂e/kWh) | L3: Fuel EF (kg CO₂e/L) | M3: Use-Phase EF – Electricity (kg CO₂e/unit lifetime) | N3: Use-Phase EF – Fuel (kg CO₂e/unit lifetime) | O3: Total Emissions – Electricity (tCO₂e) | P3: Total Emissions – Fuel (tCO₂e) | Q3: Grand Total Use-Phase Emissions (tCO₂e) | R3: Market / Region | S3: Calculation Method
A4: 1 | B4: 2023 | C4: Diesel | D4: SKU-70000 | E4: 9546 | F4: 8 | G4: 0 | H4: 0 | I4: 1200 | J4: Natural Gas | K4: 0.7426 | L4: 2.707 | M4: 0 | N4: 25987.2 | O4: 0 | P4: 248073.81 | Q4: 248073.81 | R4: EU | S4: Product spec
A5: 2 | B5: 2023 | C5: Electric | D5: SKU-70001 | E5: 3761 | F5: 12 | G5: 2000 | H5: 24000 | I5: 0 | J5: N/A | K5: 0.7011 | L5: 2.229 | M5: 16826.4 | N5: 0 | O5: 63284.09 | P5: 0 | Q5: 63284.09 | R5: Sub-Saharan Africa | S5: Customer survey
A6: 3 | B6: 2023 | C6: Air | D6: SKU-70002 | E6: 24837 | F6: 15 | G6: 1200 | H6: 18000 | I6: 0 | J6: N/A | K6: 0.6945 | L6: 2.866 | M6: 12501 | N6: 0 | O6: 310487.34 | P6: 0 | Q6: 310487.34 | R6: ASEAN | S6: Average-data
A7: 4 | B7: 2023 | C7: Refrigerator | D7: SKU-70003 | E7: 46067 | F7: 10 | G7: 400 | H7: 4000 | I7: 0 | J7: N/A | K7: 0.3998 | L7: 2.74 | M7: 1599.2 | N7: 0 | O7: 73670.35 | P7: 0 | Q7: 73670.35 | R7: ASEAN | S7: Customer survey
A8: 5 | B8: 2023 | C8: Air | D8: SKU-70004 | E8: 2078 | F8: 15 | G8: 1200 | H8: 18000 | I8: 0 | J8: N/A | K8: 0.419 | L8: 2.255 | M8: 7542 | N8: 0 | O8: 15672.28 | P8: 0 | Q8: 15672.28 | R8: EU | S8: Product spec
A9: 6 | B9: 2023 | C9: Refrigerator | D9: SKU-70005 | E9: 37401 | F9: 10 | G9: 400 | H9: 4000 | I9: 0 | J9: N/A | K9: 0.7406 | L9: 2.558 | M9: 2962.4 | N9: 0 | O9: 110796.72 | P9: 0 | Q9: 110796.72 | R9: China | S9: Product spec
A10: 7 | B10: 2023 | C10: Diesel | D10: SKU-70006 | E10: 48829 | F10: 8 | G10: 0 | H10: 0 | I10: 1200 | J10: LPG | K10: 0.4159 | L10: 2.68 | M10: 0 | N10: 25728 | O10: 0 | P10: 1256272.5 | Q10: 1256272.5 | R10: ASEAN | S10: Average-data
A11: 8 | B11: 2023 | C11: LED | D11: SKU-70007 | E11: 29196 | F11: 8 | G11: 40 | H11: 320 | I11: 0 | J11: N/A | K11: 0.7173 | L11: 2.865 | M11: 229.54 | N11: 0 | O11: 6701.65 | P11: 0 | Q11: 6701.65 | R11: USA | S11: Product spec
A12: 9 | B12: 2023 | C12: Air | D12: SKU-70008 | E12: 4032 | F12: 15 | G12: 1200 | H12: 18000 | I12: 0 | J12: N/A | K12: 0.7641 | L12: 2.135 | M12: 13753.8 | N12: 0 | O12: 55455.32 | P12: 0 | Q12: 55455.32 | R12: China | S12: Product spec
A13: 10 | B13: 2023 | C13: Industrial | D13: SKU-70009 | E13: 10608 | F13: 20 | G13: 0 | H13: 0 | I13: 5000 | J13: Natural Gas | K13: 0.3551 | L13: 3.016 | M13: 0 | N13: 301600 | O13: 0 | P13: 3199372.8 | Q13: 3199372.8 | R13: Middle East | S13: Customer survey
A14: 11 | B14: 2023 | C14: Laptop | D14: SKU-70010 | E14: 37590 | F14: 4 | G14: 60 | H14: 240 | I14: 0 | J14: N/A | K14: 0.5859 | L14: 2.88 | M14: 140.62 | N14: 0 | O14: 5285.91 | P14: 0 | Q14: 5285.91 | R14: ASEAN | S14: Product spec
A15: 12 | B15: 2023 | C15: Laptop | D15: SKU-70011 | E15: 6125 | F15: 4 | G15: 60 | H15: 240 | I15: 0 | J15: N/A | K15: 0.5951 | L15: 3.176 | M15: 142.82 | N15: 0 | O15: 874.77 | P15: 0 | Q15: 874.77 | R15: EU | S15: Customer survey
... A103: 100 | B103: 2023 | C103: Washing | D103: SKU-70099 | E103: 29552 | F103: 12 | G103: 150 | H103: 1800 | I103: 0 | J103: N/A | K103: 0.4286 | L103: 2.137 | M103: 771.48 | N103: 0 | O103: 22798.78 | P103: 0 | Q103: 22798.78 | R103: Middle East | S103: Average-data

Sheet Cat 12 – End-of-Life Treatmen
A1: Scope 3 – Category 12: End-of-Life Treatment of Sold Products
A2: GHG Protocol Corporate Value Chain (Scope 3) Accounting and Reporting Standard | Practice Dataset – 100 Rows
A3: Row # | B3: Reporting Year | C3: Quarter | D3: Product Category | E3: Product SKU | F3: Mass of Products Sold (tonne) | G3: Material Composition | H3: % to Landfill | I3: % to Incineration | J3: % to Recycling | K3: % to Composting | L3: % to Other | M3: Landfill EF (kg CO₂e/tonne) | N3: Incineration EF (kg CO₂e/tonne) | O3: Recycling EF (kg CO₂e/tonne) | P3: Composting EF (kg CO₂e/tonne) | Q3: Landfill Emissions (tCO₂e) | R3: Incineration Emissions (tCO₂e) | S3: Recycling Emissions (tCO₂e) | T3: Total EOL Emissions (tCO₂e)
A4: 1 | B4: 2023 | C4: Q1 | D4: Home Appliance | E4: SKU-80000 | F4: 293.85 | G4: Mixed Organic | H4: 28 | I4: 24 | J4: 36 | K4: 12 | L4: 0 | M4: 1195.7 | N4: 2400.8 | O4: 84.3 | P4: 239.3 | Q4: 98.3798 | R4: 169.314 | S4: 8.9178 | T4: 276.6116
A5: 2 | B5: 2023 | C5: Q2 | D5: Office Furniture | E5: SKU-80001 | F5: 404.71 | G5: Metal | H5: 37 | I5: 30 | J5: 15 | K5: 18 | L5: 0 | M5: 754.1 | N5: 645.3 | O5: 102 | P5: 228.8 | Q5: 112.921 | R5: 78.3478 | S5: 6.1921 | T5: 197.4609
A6: 3 | B6: 2023 | C6: Q3 | D6: Metal Can | E6: SKU-80002 | F6: 5.81 | G6: Metal | H6: 54 | I6: 5 | J6: 32 | K6: 9 | L6: 0 | M6: 729.5 | N6: 1430.8 | O6: 121.3 | P6: 439.5 | Q6: 2.2887 | R6: 0.4156 | S6: 0.2255 | T6: 2.9298
A7: 4 | B7: 2023 | C7: Q4 | D7: Home Appliance | E7: SKU-80003 | F7: 193.41 | G7: Ceramic | H7: 48 | I7: 11 | J7: 26 | K7: 15 | L7: 0 | M7: 634.8 | N7: 1621.9 | O7: 110.3 | P7: 458.5 | Q7: 58.9328 | R7: 34.5061 | S7: 5.5466 | T7: 98.9855
A8: 5 | B8: 2023 | C8: Q1 | D8: Plastic Bottle | E8: SKU-80004 | F8: 446.44 | G8: Textile | H8: 36 | I8: 26 | J8: 34 | K8: 4 | L8: 0 | M8: 819.9 | N8: 2126.8 | O8: 37.7 | P8: 99.9 | Q8: 131.773 | R8: 246.867 | S8: 5.7225 | T8: 384.3625
A9: 6 | B9: 2023 | C9: Q2 | D9: Glass Container | E9: SKU-80005 | F9: 24.35 | G9: Plastic | H9: 27 | I9: 18 | J9: 13 | K9: 42 | L9: 0 | M9: 555.5 | N9: 842.3 | O9: 55.8 | P9: 233.1 | Q9: 3.6521 | R9: 3.6918 | S9: 0.1766 | T9: 7.5205
A10: 7 | B10: 2023 | C10: Q3 | D10: Garment | E10: SKU-80006 | F10: 143.23 | G10: Plastic | H10: 51 | I10: 30 | J10: 37 | K10: 0 | L10: 0 | M10: 939.4 | N10: 509.3 | O10: 74.6 | P10: 132.4 | Q10: 68.6206 | R10: 21.8841 | S10: 3.9534 | T10: 94.4581
A11: 8 | B11: 2023 | C11: Q4 | D11: Industrial Equipment | E11: SKU-80007 | F11: 448.02 | G11: Glass | H11: 43 | I11: 6 | J11: 20 | K11: 31 | L11: 0 | M11: 998.1 | N11: 638.9 | O11: 23.3 | P11: 401 | Q11: 192.2826 | R11: 17.1744 | S11: 2.0878 | T11: 211.5448
A12: 9 | B12: 2023 | C12: Q1 | D12: Plastic Bottle | E12: SKU-80008 | F12: 159.28 | G12: Textile | H12: 32 | I12: 17 | J12: 12 | K12: 39 | L12: 0 | M12: 923 | N12: 1126.3 | O12: 95.7 | P12: 237.3 | Q12: 47.0449 | R12: 30.4975 | S12: 1.8292 | T12: 79.3716
A13: 10 | B13: 2023 | C13: Q2 | D13: Home Appliance | E13: SKU-80009 | F13: 424.49 | G13: Electronic Components | H13: 17 | I13: 16 | J13: 40 | K13: 27 | L13: 0 | M13: 975.3 | N13: 558.6 | O13: 16.7 | P13: 84.2 | Q13: 70.3809 | R13: 37.9392 | S13: 2.8356 | T13: 111.1557
A14: 11 | B14: 2023 | C14: Q3 | D14: Metal Can | E14: SKU-80010 | F14: 430.83 | G14: Plastic | H14: 56 | I14: 18 | J14: 17 | K14: 9 | L14: 0 | M14: 594.7 | N14: 882.3 | O14: 136.3 | P14: 227.6 | Q14: 143.4802 | R14: 68.4218 | S14: 9.9828 | T14: 221.8848
A15: 12 | B15: 2023 | C15: Q4 | D15: Office Furniture | E15: SKU-80011 | F15: 467.12 | G15: Ceramic | H15: 13 | I15: 13 | J15: 38 | K15: 36 | L15: 0 | M15: 1117.2 | N15: 721.6 | O15: 142.6 | P15: 110 | Q15: 67.8426 | R15: 43.8196 | S15: 25.3123 | T15: 136.9745
... A103: 100 | B103: 2023 | C103: Q4 | D103: Industrial Equipment | E103: SKU-80099 | F103: 487.57 | G103: Mixed Organic | H103: 51 | I103: 16 | J103: 25 | K103: 8 | L103: 0 | M103: 1251.1 | N103: 1088.1 | O103: 14.4 | P103: 227.3 | Q103: 311.0994 | R103: 84.884 | S103: 1.7553 | T103: 397.7387

Sheet Cat 13 – Downstream Leased As
A1: Scope 3 – Category 13: Downstream Leased Assets
A2: GHG Protocol Corporate Value Chain (Scope 3) Accounting and Reporting Standard | Practice Dataset – 100 Rows
A3: Row # | B3: Reporting Year | C3: Quarter | D3: Asset ID | E3: Asset Type | F3: Lessee Name | G3: Lessee Industry | H3: Country | I3: Lease Term (Years) | J3: Floor Area / Units Leased | K3: Unit | L3: Energy Consumed (kWh) | M3: Fuel Consumed (GJ) | N3: Grid EF (kg CO₂e/kWh) | O3: Fuel EF (kg CO₂e/GJ) | P3: Electricity Emissions (tCO₂e) | Q3: Fuel Emissions (tCO₂e) | R3: Total Emissions (tCO₂e) | S3: Annual Rental Income (USD) | T3: Data Source
A4: 1 | B4: 2023 | C4: Q1 | D4: DL-90000 | E4: Car Park | F4: Company S | G4: Manufacturing | H4: UK | I4: 13 | J4: 352.8 | K4: m² | L4: 610993 | M4: 404.02 | N4: 0.6054 | O4: 73.43 | P4: 369.8952 | Q4: 29.6672 | R4: 399.5624 | S4: 2565502 | T4: Average-data estimate
A5: 2 | B5: 2023 | C5: Q2 | D5: DL-90001 | E5: Commercial Office | F5: Company H | G5: Government | H5: Australia | I5: 19 | J5: 6604.9 | K5: m² | L5: 154324.3 | M5: 381.31 | N5: 0.6746 | O5: 78.66 | P5: 104.1072 | Q5: 29.9938 | R5: 134.101 | S5: 4795195 | T5: Average-data estimate
A6: 3 | B6: 2023 | C6: Q3 | D6: DL-90002 | E6: Logistics Hub | F6: Company Q | G6: Education | H6: Japan | I6: 11 | J6: 7366.1 | K6: m² | L6: 541272.5 | M6: 60.62 | N6: 0.7892 | O6: 73.95 | P6: 427.1723 | Q6: 4.4828 | R6: 431.6551 | S6: 3055155 | T6: Smart meter
A7: 4 | B7: 2023 | C7: Q4 | D7: DL-90003 | E7: Cold Storage Facility | F7: Company O | G7: Manufacturing | H7: Canada | I7: 4 | J7: 8376.5 | K7: m² | L7: 296600 | M7: 122.01 | N7: 0.4715 | O7: 73.03 | P7: 139.8469 | Q7: 8.9104 | R7: 148.7573 | S7: 1841727 | T7: Average-data estimate
A8: 5 | B8: 2023 | C8: Q1 | D8: DL-90004 | E8: Cold Storage Facility | F8: Company L | G8: Hospitality | H8: UAE | I8: 8 | J8: 4505.6 | K8: m² | L8: 957820.5 | M8: 204.96 | N8: 0.3898 | O8: 66.81 | P8: 373.3584 | Q8: 13.6934 | R8: 387.0518 | S8: 428397 | T8: Smart meter
A9: 6 | B9: 2023 | C9: Q2 | D9: DL-90005 | E9: Leased Vehicle Fleet | F9: Company S | G9: Healthcare | H9: UAE | I9: 9 | J9: 2374.7 | K9: vehicles | L9: 828682 | M9: 493.37 | N9: 0.8129 | O9: 57.35 | P9: 673.6356 | Q9: 28.2948 | R9: 701.9304 | S9: 4550865 | T9: Smart meter
A10: 7 | B10: 2023 | C10: Q3 | D10: DL-90006 | E10: Residential Block | F10: Company G | G10: Healthcare | H10: Mexico | I10: 15 | J10: 3207.1 | K10: m² | L10: 86098.4 | M10: 210.51 | N10: 0.8416 | O10: 67.28 | P10: 72.4604 | Q10: 14.1631 | R10: 86.6235 | S10: 3181517 | T10: Lessee-reported
A11: 8 | B11: 2023 | C11: Q4 | D11: DL-90007 | E11: Industrial Warehouse | F11: Company B | G11: Logistics | H11: India | I11: 23 | J11: 1295.8 | K11: m² | L11: 267059.2 | M11: 277.29 | N11: 0.8151 | O11: 72.29 | P11: 217.68 | Q11: 20.0453 | R11: 237.7253 | S11: 675670 | T11: Lessee-reported
A12: 9 | B12: 2023 | C12: Q1 | D12: DL-90008 | E12: Retail Mall Unit | F12: Company R | G12: FMCG | H12: Canada | I12: 10 | J12: 1410.5 | K12: m² | L12: 867545.6 | M12: 459.31 | N12: 0.8021 | O12: 60.63 | P12: 695.8583 | Q12: 27.848 | R12: 723.7063 | S12: 2041472 | T12: Lessee-reported
A13: 10 | B13: 2023 | C13: Q2 | D13: DL-90009 | E13: Residential Block | F13: Company L | G13: Hospitality | H13: Mexico | I13: 14 | J13: 8984.5 | K13: m² | L13: 898862.1 | M13: 295.74 | N13: 0.6583 | O13: 79.82 | P13: 591.7209 | Q13: 23.606 | R13: 615.3269 | S13: 273927 | T13: Average-data estimate
A14: 11 | B14: 2023 | C14: Q3 | D14: DL-90010 | E14: Co-working Space | F14: Company S | G14: Education | H14: USA | I14: 5 | J14: 7432.9 | K14: m² | L14: 438511.7 | M14: 378.83 | N14: 0.7001 | O14: 72 | P14: 307.002 | Q14: 27.2758 | R14: 334.2778 | S14: 3632352 | T14: Lessee-reported
A15: 12 | B15: 2023 | C15: Q4 | D15: DL-90011 | E15: Car Park | F15: Company I | G15: Technology | H15: UK | I15: 10 | J15: 5971.2 | K15: m² | L15: 675537.6 | M15: 226.76 | N15: 0.5102 | O15: 55.3 | P15: 344.6593 | Q15: 12.5398 | R15: 357.1991 | S15: 3626539 | T15: Smart meter
... A103: 100 | B103: 2023 | C103: Q4 | D103: DL-90099 | E103: Residential Block | F103: Company N | G103: Logistics | H103: UK | I103: 21 | J103: 7653.1 | K103: m² | L103: 657909.7 | M103: 341.68 | N103: 0.3992 | O103: 67.4 | P103: 262.6376 | Q103: 23.0292 | R103: 285.6668 | S103: 2119595 | T103: Lessee-reported

Sheet Cat 14 – Franchises
A1: Scope 3 – Category 14: Franchises
A2: GHG Protocol Corporate Value Chain (Scope 3) Accounting and Reporting Standard | Practice Dataset – 100 Rows
A3: Row # | B3: Reporting Year | C3: Quarter | D3: Franchise Location ID | E3: Franchise Brand | F3: City | G3: Country | H3: Outlet Type | I3: Floor Area (m²) | J3: Number of Employees | K3: Electricity Consumed (kWh) | L3: Natural Gas Consumed (GJ) | M3: Refrigerant Leakage (kg CO₂e) | N3: Grid EF (kg CO₂e/kWh) | O3: Gas EF (kg CO₂e/GJ) | P3: Scope 1 – Fuel Emissions (tCO₂e) | Q3: Scope 1 – Refrigerant (tCO₂e) | R3: Scope 2 – Electricity Emissions (tCO₂e) | S3: Total Franchise Emissions (tCO₂e) | T3: Reporting Quality
A4: 1 | B4: 2023 | C4: Q1 | D4: FR-40000 | E4: BrandX Quick Service | F4: Dhaka | G4: UAE | H4: Hotel Franchisee | I4: 514.2 | J4: 13 | K4: 114122.2 | L4: 142.18 | M4: 40.3 | N4: 0.6353 | O4: 56.82 | P4: 8.0787 | Q4: 0.0403 | R4: 72.5018 | S4: 80.6208 | T4: Franchisee reported
A5: 2 | B5: 2023 | C5: Q2 | D5: FR-40001 | E5: BrandX Drive-Through | F5: Cairo | G5: Australia | H5: Hotel Franchisee | I5: 477 | J5: 35 | K5: 112988.2 | L5: 228.16 | M5: 11.4 | N5: 0.6507 | O5: 57.58 | P5: 13.1375 | Q5: 0.0114 | R5: 73.5214 | S5: 86.6703 | T5: Franchisee reported
A6: 3 | B6: 2023 | C6: Q3 | D6: FR-40002 | E6: BrandX Express | F6: Lagos | G6: Mexico | H6: High Street Restaurant | I6: 393.3 | J6: 51 | K6: 108130 | L6: 50.67 | M6: 468.6 | N6: 0.8107 | O6: 56.65 | P6: 2.8705 | Q6: 0.4686 | R6: 87.661 | S6: 91.0001 | T6: Franchisee reported
A7: 4 | B7: 2023 | C7: Q4 | D7: FR-40003 | E7: BrandX Premium | F7: Lima | G7: USA | H7: Convenience Store | I7: 483.2 | J7: 34 | K7: 72001.3 | L7: 155.33 | M7: 494.9 | N7: 0.7484 | O7: 57.95 | P7: 9.0014 | Q7: 0.4949 | R7: 53.8858 | S7: 63.3821 | T7: Franchisee reported
A8: 5 | B8: 2023 | C8: Q1 | D8: FR-40004 | E8: BrandX Drive-Through | F8: Karachi | G8: USA | H8: Airport Lounge | I8: 233.6 | J8: 51 | K8: 68326.8 | L8: 12.4 | M8: 16.2 | N8: 0.6884 | O8: 57.73 | P8: 0.7159 | Q8: 0.0162 | R8: 47.0362 | S8: 47.7683 | T8: Estimated from benchmarks
A9: 6 | B9: 2023 | C9: Q2 | D9: FR-40005 | E9: BrandX Drive-Through | F9: Bangkok | G9: India | H9: Petrol Station | I9: 712.5 | J9: 39 | K9: 88489.9 | L9: 284.62 | M9: 323.5 | N9: 0.6171 | O9: 56.05 | P9: 15.953 | Q9: 0.3235 | R9: 54.6071 | S9: 70.8836 | T9: Estimated from benchmarks
A10: 7 | B10: 2023 | C10: Q3 | D10: FR-40006 | E10: BrandX Drive-Through | F10: Ho Chi Minh City | G10: USA | H10: Food Court Kiosk | I10: 671.2 | J10: 51 | K10: 170318.5 | L10: 143.31 | M10: 358.3 | N10: 0.6058 | O10: 57.3 | P10: 8.2117 | Q10: 0.3583 | R10: 103.1789 | S10: 111.7489 | T10: Franchisee reported
A11: 8 | B11: 2023 | C11: Q4 | D11: FR-40007 | E11: BrandX Express | F11: Jakarta | G11: Mexico | H11: Hotel Franchisee | I11: 685.3 | J11: 53 | K11: 181635.8 | L11: 266.66 | M11: 55.9 | N11: 0.4345 | O11: 56.83 | P11: 15.1543 | Q11: 0.0559 | R11: 78.9208 | S11: 94.131 | T11: Estimated from benchmarks
A12: 9 | B12: 2023 | C12: Q1 | D12: FR-40008 | E12: BrandX Express | F12: Dhaka | G12: China | H12: Hospital Cafeteria | I12: 207.6 | J12: 11 | K12: 34462.7 | L12: 75.19 | M12: 229.1 | N12: 0.7045 | O12: 57.51 | P12: 4.3242 | Q12: 0.2291 | R12: 24.279 | S12: 28.8323 | T12: Estimated from benchmarks
A13: 10 | B13: 2023 | C13: Q2 | D13: FR-40009 | E13: BrandX Quick Service | F13: São Paulo | G13: Mexico | H13: Convenience Store | I13: 640.5 | J13: 49 | K13: 97089.8 | L13: 111.37 | M13: 17.9 | N13: 0.42 | O13: 57.04 | P13: 6.3525 | Q13: 0.0179 | R13: 40.7777 | S13: 47.1481 | T13: Utility bill
A14: 11 | B14: 2023 | C14: Q3 | D14: FR-40010 | E14: BrandX Express | F14: Jakarta | G14: Canada | H14: Drive-Through | I14: 322 | J14: 23 | K14: 51949.1 | L14: 119.82 | M14: 283.8 | N14: 0.5024 | O14: 57.43 | P14: 6.8813 | Q14: 0.2838 | R14: 26.0992 | S14: 33.2643 | T14: Franchisee reported
A15: 12 | B15: 2023 | C15: Q4 | D15: FR-40011 | E15: BrandX Premium | F15: Mumbai | G15: China | H15: Convenience Store | I15: 505.6 | J15: 59 | K15: 89413 | L15: 170.16 | M15: 14 | N15: 0.4558 | O15: 56.61 | P15: 9.6328 | Q15: 0.014 | R15: 40.7544 | S15: 50.4012 | T15: Utility bill
... A103: 100 | B103: 2023 | C103: Q4 | D103: FR-40099 | E103: BrandX Premium | F103: Dhaka | G103: Japan | H103: Airport Lounge | I103: 130.8 | J103: 48 | K103: 17799.7 | L103: 37.06 | M103: 450.1 | N103: 0.5988 | O103: 57.21 | P103: 2.1202 | Q103: 0.4501 | R103: 10.6585 | S103: 13.2288 | T103: Estimated from benchmarks

Sheet Cat 15 – Investments
A1: Scope 3 – Category 15: Investments
A2: GHG Protocol Corporate Value Chain (Scope 3) Accounting and Reporting Standard | Practice Dataset – 100 Rows
A3: Row # | B3: Reporting Year | C3: Investee / Borrower | D3: Country | E3: Asset Class | F3: Sector | G3: Investment Type | H3: Outstanding Amount (USD mn) | I3: Investee EVIC (USD mn) | J3: Attribution Factor (%) | K3: Investee Scope 1 (tCO₂e) | L3: Investee Scope 2 (tCO₂e) | M3: Investee Scope 1+2 (tCO₂e) | N3: Attributed Emissions (tCO₂e) | O3: Investee Revenue (USD mn) | P3: Emission Intensity (tCO₂e/USD mn revenue) | Q3: PCAF Data Quality Score (1–5) | R3: Data Source | S3: Notes
A4: 1 | B4: 2023 | C4: InvestCo P Ltd | D4: UK | E4: SME Loan | F4: Oil & Gas | G4: Debt | H4: 472.06 | I4: 6547.97 | J4: 7.21 | K4: 33666 | L4: 49621 | M4: 83287 | N4: 6004.99 | O4: 1302.83 | P4: 63.93 | Q4: 1 | R4: Refinitiv | S4: Estimated via sector avg
A5: 2 | B5: 2023 | C5: InvestCo K Ltd | D5: Mexico | E5: Infrastructure | F5: Financial Services | G5: Blended Finance | H5: 354.11 | I5: 6027.89 | J5: 5.87 | K5: 50291 | L5: 104209 | M5: 154500 | N5: 9069.15 | O5: 3402.5 | P5: 45.41 | Q5: 5 | R5: Estimated | S5: Self-reported
A6: 3 | B6: 2023 | C6: InvestCo J Ltd | D6: France | E6: SME Loan | F6: Aviation | G6: Debt | H6: 378.7 | I6: 5074.27 | J6: 7.46 | K6: 141998 | L6: 27527 | M6: 169525 | N6: 12646.57 | O6: 3219.45 | P6: 52.66 | Q6: 4 | R6: CDP disclosure | S6: Self-reported
A7: 4 | B7: 2023 | C7: InvestCo Y Ltd | D7: China | E7: Listed Equity | F7: Agriculture | G7: Equity | H7: 12.89 | I7: 44.21 | J7: 29.16 | K7: 281065 | L7: 122128 | M7: 403193 | N7: 117571.08 | O7: 13.89 | P7: 29027.57 | Q7: 2 | R7: CDP disclosure | S7: Self-reported
A8: 5 | B8: 2023 | C8: InvestCo B Ltd | D8: Australia | E8: Listed Equity | F8: Oil & Gas | G8: Debt | H8: 446.15 | I8: 6841.82 | J8: 6.52 | K8: 286066 | L8: 35085 | M8: 321151 | N8: 20939.05 | O8: 2186.36 | P8: 146.89 | Q8: 4 | R8: Annual report | S8: Self-reported
A9: 6 | B9: 2023 | C9: InvestCo Q Ltd | D9: Netherlands | E9: Project Finance | F9: Agriculture | G9: Debt | H9: 482.13 | I9: 1190.89 | J9: 40.48 | K9: 412872 | L9: 174804 | M9: 587676 | N9: 237891.24 | O9: 734.75 | P9: 799.83 | Q9: 1 | R9: Annual report | S9: Audited Scope data
A10: 7 | B10: 2023 | C10: InvestCo P Ltd | D10: UK | E10: Listed Equity | F10: Oil & Gas | G10: Debt | H10: 229.16 | I10: 1131.03 | J10: 20.26 | K10: 111562 | L10: 64402 | M10: 175964 | N10: 35650.31 | O10: 678.42 | P10: 259.37 | Q10: 2 | R10: CDP disclosure | S10: Self-reported
A11: 8 | B11: 2023 | C11: InvestCo M Ltd | D11: Netherlands | E11: Real Estate | F11: Automotive | G11: Debt | H11: 3.36 | I11: 19.98 | J11: 16.82 | K11: 407005 | L11: 166345 | M11: 573350 | N11: 96437.47 | O11: 15.77 | P11: 36357.01 | Q11: 1 | R11: Annual report | S11: Audited Scope data
A12: 9 | B12: 2023 | C12: InvestCo W Ltd | D12: Netherlands | E12: Unlisted Equity | F12: Cement | G12: Blended Finance | H12: 299.78 | I12: 3897.93 | J12: 7.69 | K12: 129834 | L12: 184474 | M12: 314308 | N12: 24170.29 | O12: 2246.29 | P12: 139.92 | Q12: 3 | R12: Refinitiv | S12: Estimated via sector avg
A13: 10 | B13: 2023 | C13: InvestCo Y Ltd | D13: Japan | E13: Unlisted Equity | F13: Financial Services | G13: Equity | H13: 6.1 | I13: 102.09 | J13: 5.98 | K13: 189189 | L13: 168606 | M13: 357795 | N13: 21396.14 | O13: 23.75 | P13: 15065.05 | Q13: 4 | R13: CDP disclosure | S13: Estimated via sector avg
A14: 11 | B14: 2023 | C14: InvestCo F Ltd | D14: Mexico | E14: Mortgage | F14: Utilities | G14: Equity | H14: 383.8 | I14: 1490.85 | J14: 25.74 | K14: 345060 | L14: 14570 | M14: 359630 | N14: 92568.76 | O14: 268.45 | P14: 1339.65 | Q14: 5 | R14: Bloomberg ESG | S14: Audited Scope data
A15: 12 | B15: 2023 | C15: InvestCo R Ltd | D15: China | E15: Unlisted Equity | F15: Mining | G15: Blended Finance | H15: 471.81 | I15: 2946.56 | J15: 16.01 | K15: 340772 | L15: 186159 | M15: 526931 | N15: 84361.65 | O15: 1115.99 | P15: 472.16 | Q15: 3 | R15: CDP disclosure | S15: Audited Scope data
... A103: 100 | B103: 2023 | C103: InvestCo W Ltd | D103: Mexico | E103: Corporate Bond | F103: Utilities | G103: Equity | H103: 112.49 | I103: 1970.03 | J103: 5.71 | K103: 292201 | L103: 98924 | M103: 391125 | N103: 22333.24 | O103: 1181.39 | P103: 331.07 | Q103: 2 | R103: Annual report | S103: Estimated via sector avg

Sheet Summary – Definitions & Methods
A1: GHG Protocol – Scope 3 Categories: Definitions & Calculation Methodologies
A2: Source: GHG Protocol Corporate Value Chain (Scope 3) Accounting and Reporting Standard (2011 + 2023 Tech. Update) | PCAF Global GHG Accounting and Reporting Standard (2022)
A4: Cat # | B4: Category Name | C4: Upstream / Downstream | D4: Relevance | E4: Definition (GHG Protocol) | F4: Calculation Methodology (GHG Protocol) | G4: Key Emission Factors | H4: Common Data Sources | I4: Linked Dataset Tab
A5: 1 | B5: Purchased Goods & Services | C5: Upstream | D5: Often material for product companies | E5: Scope 3, Category 1 covers emissions from the extraction, production, and transportation of goods and services purchased or acquired by the reporting company in the reporting year. This includes raw materials, components, packaging, and purchased services (e.g., professional services, IT services). Emissions occur upstream of the company's operations. | F5: Calculation Methods (GHG Protocol Scope 3 Standard, Chapter 5): 1. Spend-based: Activity data (spend, USD) × Supplier- or industry-average spend-based emission factor (kg CO₂e/USD). 2. Average-data: Mass/volume of goods purchased × average emission factor per unit mass/volume (kg CO₂e/kg or kg CO₂e/unit). 3. Supplier-specific: Use primary data (emissions disclosed by suppliers). 4. Hybrid: Combination of supplier-specific and average-data methods. Emission factor sources: Ecoinvent, US EPA USEEIO, EXIOBASE, supplier EPDs. | G5: Ecoinvent, USEEIO, EXIOBASE, Supplier EPDs | H5: Supplier invoices, procurement data, EPDs | I5: Cat 1 – Purchased Goods & Se…
A6: 2 | B6: Capital Goods | C6: Upstream | D6: Material for capex-intensive industries | E6: Scope 3, Category 2 covers emissions from the extraction, production, and transportation of capital goods purchased or acquired by the reporting company in the reporting year. Capital goods are final products with extended life that are used by the company to produce a product, provide a service, or sell, store, and deliver merchandise (e.g., machinery, equipment, buildings, vehicles). | F6: Calculation Methods (GHG Protocol Scope 3 Standard, Chapter 5): 1. Spend-based: Capital expenditure (USD) × spend-based emission factor (kg CO₂e/USD) for the relevant capital goods sector. 2. Average-data: Mass or physical units × average emission factor (kg CO₂e/kg or per unit). 3. Supplier-specific: Actual lifecycle emissions disclosed by equipment supplier or obtained from EPD. Note: Do NOT depreciate capital goods emissions; count full upstream emissions in the year of acquisition. | G6: Ecoinvent, Supplier EPDs, USEEIO | H6: Capex ledger, asset register, supplier EPDs | I6: Cat 2 – Capital Goods…
A7: 3 | B7: Fuel- and Energy-Related Activities | C7: Upstream | D7: Material for energy-intensive operations | E7: Scope 3, Category 3 covers emissions that are not included in Scope 1 or Scope 2 but result from the extraction, production, and transportation of fuels and energy consumed by the reporting company. This includes: (a) upstream emissions from extraction and production of purchased fuels; (b) upstream emissions from extraction and production of purchased electricity, heat, steam, and cooling; (c) transmission and distribution (T&D) losses; and (d) emissions from generation of purchased electricity that is sold to end users (relevant only for electric utilities). | F7: Calculation Methods (GHG Protocol Scope 3 Standard, Chapter 5): 1. Upstream fuel emissions: Fuel consumed (GJ or L) × upstream emission factor (kg CO₂e/GJ). 2. Upstream electricity emissions: Electricity consumed (MWh) × upstream emission factor (kg CO₂e/MWh, covering extraction and processing of primary fuel used to generate electricity). 3. T&D losses: Electricity purchased (MWh) × T&D loss factor × grid emission factor (kg CO₂e/MWh). Sources: IEA, IPCC, national energy statistics, utility disclosures. | G7: IEA, IPCC AR6, National energy statistics | H7: Utility bills, meter data, energy audits | I7: Cat 3 – Fuel- and Energy-Rel…
A8: 4 | B8: Upstream Transportation & Distribution | C8: Upstream | D8: Relevant for companies with global supply chains | E8: Scope 3, Category 4 covers emissions from transportation and distribution of products (including imported goods) from tier-1 suppliers to the reporting company's operations, between the company's own facilities, and to intermediaries (e.g., distributors, retailers) but NOT to end consumers (which falls under Category 9). This includes all modes: road, rail, air, and maritime transport. | F8: Calculation Methods (GHG Protocol Scope 3 Standard, Chapter 5): 1. Distance-based: Mass transported (tonne) × distance (km) × emission factor (kg CO₂e/tonne-km) for transport mode. 2. Spend-based: Logistics spend (USD) × spend-based emission factor (kg CO₂e/USD). 3. Fuel-based: Fuel consumed by transport vehicle (L) × fuel emission factor (kg CO₂e/L). Emission factors by mode (GLEC Framework / IPCC): Road ~0.062–0.200, Rail ~0.022–0.028, Sea ~0.010–0.040, Air ~0.600–2.100 kg CO₂e/tonne-km. | G8: GLEC Framework, IPCC, ICAO | H8: Logistics invoices, BOL, carrier data | I8: Cat 4 – Upstream Transportat…
A9: 5 | B9: Waste Generated in Operations | C9: Upstream | D9: Relevant for manufacturing & chemical industries | E9: Scope 3, Category 5 covers emissions from third-party disposal and treatment of solid and liquid waste that is generated in the reporting company's operations. This includes waste sent to landfill, incineration, composting, anaerobic digestion, wastewater treatment, and recycling. Emissions occur at the waste treatment facility, not at the company's site. | F9: Calculation Methods (GHG Protocol Scope 3 Standard, Chapter 5): 1. Waste-type-specific: Mass of waste (tonne) × waste-type-specific emission factor per treatment method (kg CO₂e/tonne). Landfill: ~0.45–1.30 kg CO₂e/kg (methane from decomposition). Incineration: ~0.50–2.50 kg CO₂e/kg (varies by waste composition). Composting: ~0.08–0.48 kg CO₂e/kg. Recycling: ~0.01–0.15 kg CO₂e/kg. 2. Average-data: Total waste (tonne) × average emission factor across typical waste mix. Sources: IPCC Waste Module, US EPA WARM Model, national waste statistics. | G9: IPCC Waste, US EPA WARM, EU Waste Stats | H9: Waste manifests, contractor invoices | I9: Cat 5 – Waste Generated in O…
A10: 6 | B10: Business Travel | C10: Upstream | D10: Relevant for professional services, airlines | E10: Scope 3, Category 6 covers emissions from the transportation of employees for business-related activities during the reporting year. This includes air travel, rail, bus, taxi/rideshare, rental cars, and personal vehicle use for business purposes. Hotel stays are also included under this category. | F10: Calculation Methods (GHG Protocol Scope 3 Standard, Chapter 5): 1. Distance-based (air): Passenger-km × emission factor (kg CO₂e/pkm) by class (economy, business, first) and haul length. Short-haul economy: ~0.255 kg CO₂e/pkm (with radiative forcing: ×2). Long-haul economy: ~0.195 kg CO₂e/pkm. Business class: ~2–3× economy factor. 2. Spend-based: Travel spend (USD) × spend-based emission factor. 3. Hotel nights: Number of nights × hotel emission factor (kg CO₂e/night). Sources: DEFRA/BEIS UK GHG Conversion Factors, ICAO Carbon Estimator, IATA. | G10: DEFRA/BEIS UK Conv. Factors, ICAO CORSIA | H10: Travel booking system, expense reports | I10: Cat 6 – Business Travel…
A11: 7 | B11: Employee Commuting | C11: Upstream | D11: Material for large-headcount companies | E11: Scope 3, Category 7 covers emissions from the transportation of employees between their homes and their worksites during the reporting year. This includes all modes of transportation (car, motorcycle, bus, rail, etc.) and remote working (work-from-home) arrangements that shift energy consumption to employees' residences. | F11: Calculation Methods (GHG Protocol Scope 3 Standard, Chapter 5): 1. Distance-based: Employee-km × mode-specific emission factor (kg CO₂e/pkm). Private car: ~0.170–0.210 kg CO₂e/pkm (petrol). Electric vehicle: ~0.050–0.090 kg CO₂e/pkm (grid-dependent). Public bus: ~0.089–0.105 kg CO₂e/pkm. Metro/rail: ~0.041 kg CO₂e/pkm. 2. Survey-based: Collect data on commute mode share, distance, and frequency from employee surveys, then apply distance-based method. 3. Spend-based: Employee transport subsidy spend × emission factor. Remote-work emissions: Estimate home energy use attributable to work activity. | G11: DEFRA/BEIS, National transport stats | H11: Employee surveys, HR records, payroll | I11: Cat 7 – Employee Commuting…
A12: 8 | B12: Upstream Leased Assets | C12: Upstream | D12: Relevant for office-based companies (equity approach) | E12: Scope 3, Category 8 covers emissions from the operation of assets leased by the reporting company (lessee) that are not already included in Scope 1 or Scope 2. This applies when the company uses the equity-share or financial control approach for Scope 1 and 2 reporting. Typical assets: leased office space, leased vehicles, leased equipment where the lessor controls the asset. | F12: Calculation Methods (GHG Protocol Scope 3 Standard, Chapter 5): 1. Asset-specific: Actual energy consumption of the leased asset × appropriate emission factor (for electricity: grid EF; for fuels: combustion EF). 2. Lessor-reported: Emissions as disclosed by the lessor. 3. Average-data: Floor area of leased space (m²) × average energy intensity (kWh/m²/yr) × emission factor; or vehicle-km × vehicle emission factor. Note: If operational control approach is used for Scope 1/2, leased asset emissions are typically already in Scope 1/2 and NOT in Category 8. | G12: National grid EF, IPCC combustion EFs | H12: Lessor energy statements, meter data | I12: Cat 8 – Upstream Leased Asse…
A13: 9 | B13: Downstream Transportation & Distribution | C13: Downstream | D13: Relevant for product manufacturers & retailers | E13: Scope 3, Category 9 covers emissions from transportation and distribution of products sold by the reporting company in the reporting year, from the point of sale to the end consumer. This includes transport by third-party carriers and distributors, retail storage, and last-mile delivery. It differs from Category 4 in that it covers outbound logistics beyond the point of sale. | F13: Calculation Methods (GHG Protocol Scope 3 Standard, Chapter 5): 1. Distance-based: Mass of product sold (tonne) × transport distance (km) × mode emission factor (kg CO₂e/tonne-km). 2. Spend-based: Outbound logistics spend (USD) × spend-based EF. 3. Fuel-based: Fuel consumed by outbound vehicles × fuel EF (kg CO₂e/L). Also includes energy used in intermediate storage/warehousing: Warehouse area (m²) × energy intensity × grid EF. Mode emission factors (GLEC/IPCC): Road ~0.100, Rail ~0.028, Air ~0.800–2.000, Sea ~0.012 kg CO₂e/tonne-km. | G13: GLEC Framework, IPCC Transport | H13: Outbound logistics invoices, WMS data | I13: Cat 9 – Downstream Transport…
A14: 10 | B14: Processing of Sold Products | C14: Downstream | D14: Relevant only for manufacturers of intermediate goods | E14: Scope 3, Category 10 covers emissions from the processing of sold intermediate products by downstream companies (customers). It is relevant only for intermediate products that require further processing before end use. For example, a chemical company that sells a precursor chemical that must be processed by a customer before being incorporated into a final product. | F14: Calculation Methods (GHG Protocol Scope 3 Standard, Chapter 5): 1. Site-specific: Collect actual processing emission data from customers. 2. Average-data: Mass of intermediate product sold (tonne) × average processing emission factor for the product type (kg CO₂e/tonne). Example: Emissions per tonne of steel processed, per tonne of resin injection-moulded, per tonne of chemical reacted. 3. Process engineering: Use process engineering models to estimate energy and material inputs in downstream processing and apply emission factors. Applicability: Only if the company sells intermediate goods, not final products. | G14: Ecoinvent, Process engineering databases | H14: Customer process data, industry benchmarks | I14: Cat 10 – Processing of Sold P…
A15: 11 | B15: Use of Sold Products | C15: Downstream | D15: Often the largest category for product OEMs | E15: Scope 3, Category 11 covers emissions from the use of goods and services sold by the reporting company. This is often the most material Scope 3 category for manufacturers of energy-using products (e.g., vehicles, appliances, electronics, fuel). Includes: direct use-phase emissions (combustion in sold engines, electricity from sold generators) and indirect use-phase emissions (electricity consumed by sold appliances). | F15: Calculation Methods (GHG Protocol Scope 3 Standard, Chapter 5): 1. Direct use-phase: Units sold × lifetime fuel/energy consumption per unit × emission factor (kg CO₂e/L or /MWh). 2. Indirect use-phase: Units sold × annual electricity consumption (kWh/yr) × product lifetime (yr) × average grid emission factor. 3. Sold fuel: Volume of fuel sold (L) × combustion emission factor (kg CO₂e/L) — applicable to oil/gas companies and fuel retailers. Key inputs: Product lifetime, usage frequency, product energy efficiency rating, grid emission factor projections. Sources: DEFRA, IEA, product specs. | G15: IEA grid EF projections, DEFRA | H15: Product energy specs, sales records | I15: Cat 11 – Use of Sold Products…
A16: 12 | B16: End-of-Life Treatment of Sold Products | C16: Downstream | D16: Relevant for consumer goods, electronics | E16: Scope 3, Category 12 covers emissions from the waste disposal and treatment of products sold by the reporting company at the end of their life. This includes all waste treatment methods: landfill, incineration, recycling, reuse, composting, and anaerobic digestion. Emissions are allocated to the producer of the product, not the waste management company. | F16: Calculation Methods (GHG Protocol Scope 3 Standard, Chapter 5): 1. Waste-type-specific: Mass of product sold (tonne) × fraction to each disposal route × waste-type emission factor (kg CO₂e/tonne). Landfill: ~0.50–1.50 kg CO₂e/kg. Incineration: ~0.60–3.00 kg CO₂e/kg. Recycling: ~0.05–0.20 kg CO₂e/kg. 2. Average-data: Total mass of products sold (tonne) × national average waste treatment mix emission factor. Data sources: Product lifecycle data, national recycling/landfill statistics, IPCC Waste Module, US EPA WARM Model, EU waste statistics. | G16: IPCC Waste Module, US EPA WARM | H16: Waste audits, LCA reports, recycling records | I16: Cat 12 – End-of-Life Treatmen…
... A19: 15 | B19: Investments | C19: Downstream | D19: Most material for financial institutions | E19: Scope 3, Category 15 covers emissions associated with the reporting company's investments in the reporting year, not included in Scope 1 or 2. This is relevant for investors, banks, insurance companies, and any company with significant equity or debt holdings. Sub-categories: equity investments, debt investments (corporate bonds, project finance), managed investments, client services (for financial services companies), and other investments such as real assets and sovereign bonds. | F19: Calculation Methods (GHG Protocol Scope 3 Standard / PCAF Standard): 1. Equity investments: (Equity stake / Total equity + debt) × Investee's Scope 1+2 emissions. Attribution factor = Company's equity / Investee EVIC (Enterprise Value Including Cash). 2. Corporate bonds: (Outstanding amount / Investee EVIC) × Investee's Scope 1+2 emissions. 3. Project finance: (Loan amount / Total project cost) × Project Scope 1+2 emissions. 4. PCAF Data Quality Score (1–5): Prioritise DQ score 1 (reported) over DQ score 5 (modelled/estimated). Sources: PCAF Global GHG Accounting and Reporting Standard (2022), investee sustainability reports, Bloomberg, Refinitiv ESG data. | G19: PCAF DQ Score table, Bloomberg ESG, Refinitiv | H19: CDP, Annual reports, Bloomberg ESG, PCAF | I19: Cat 15 – Investments…
A20: ℹ️ Practice Instructions: Each of the 15 category tabs contains 100 rows of sample data. Use this summary as a reference to understand the calculation methodology, then apply it to compute emissions for each row. Validate totals using GHG Protocol guidance.
